alu.v
///Updiuno ALU
module alu (
    input  [31:0] operand_a,
    input  [31:0] operand_b,
  	input  [3:0]  alu_ctrl,
    output reg [31:0] result,
    output        zero
);
  
// ALUops
localparam ALU_ADD  = 4'b0000;
localparam ALU_SUB  = 4'b0001;
localparam ALU_AND  = 4'b0010;
localparam ALU_OR   = 4'b0011;
localparam ALU_XOR  = 4'b0100;
localparam ALU_SLT  = 4'b0101;  // Set Less Than
localparam ALU_SLTU = 4'b0110;  // Set Less Than Unsigned
localparam ALU_SLL  = 4'b0111;  // Shift Left Logical
localparam ALU_SRL  = 4'b1000;  // Shift Right Logical
localparam ALU_SRA  = 4'b1001;  // Shift Right Arithmetic
  
  always @(*) begin
    case (alu_ctrl) //32 bits
      	ALU_ADD:  result = operand_a + operand_b;
        ALU_SUB:  result = operand_a - operand_b;
        ALU_AND:  result = operand_a & operand_b;
        ALU_OR:   result = operand_a | operand_b;
        ALU_XOR:  result = operand_a ^ operand_b;
        ALU_SLT:  result = ($signed(operand_a) < $signed(operand_b)) ? 32'd1 : 32'd0;
        ALU_SLTU: result = (operand_a < operand_b) ? 32'd1 : 32'd0;
        ALU_SLL:  result = operand_a << operand_b[4:0];
        ALU_SRL:  result = operand_a >> operand_b[4:0];
        ALU_SRA:  result = $signed(operand_a) >>> operand_b[4:0];
        default:  result = 32'd0;
    endcase
  end
  
  assign zero = (result == 32'd0);
  
endmodule

alu_tb.v
`timescale 1ns / 1ps

module alu_tb;

  //sigs
  reg  [31:0] operand_a;
  reg  [31:0] operand_b;
  reg  [3:0]  alu_ctrl;
  wire [31:0] result;
  wire zero;
  
  localparam ALU_ADD  = 4'b0000;
  localparam ALU_SUB  = 4'b0001;
  localparam ALU_AND  = 4'b0010;
  localparam ALU_OR   = 4'b0011;
  localparam ALU_XOR  = 4'b0100;
  localparam ALU_SLT  = 4'b0101;
  localparam ALU_SLTU = 4'b0110;
  localparam ALU_SLL  = 4'b0111;
  localparam ALU_SRL  = 4'b1000;
  localparam ALU_SRA  = 4'b1001;
  
  //alu
  alu dut (
    .operand_a(operand_a),
    .operand_b(operand_b),
    .alu_ctrl(alu_ctrl),
    .result(result),
    .zero(zero)
  );

  //dump files are necessary
  initial begin
    $dumpfile("alu_tb.vcd");
    $dumpvars(0, alu_tb);
  end
  
  initial begin
    $display("Starting ALU Testbench>>>>");
    
    // Test ADD operation
    $display("\nTesting ADD operation:");
    operand_a = 32'd15; operand_b = 32'd10; alu_ctrl = ALU_ADD;
    #10;
    $display("  %d + %d = %d (Expected: 25)", operand_a, operand_b, result);
    
    operand_a = 32'hFFFFFFFF; operand_b = 32'd1; alu_ctrl = ALU_ADD;
    #10;
    $display("  0x%h + %d = 0x%h (Expected: 0, overflow)", operand_a, operand_b, result);
    
    // Test SUB operation
    $display("\nTesting SUB operation:");
    operand_a = 32'd20; operand_b = 32'd5; alu_ctrl = ALU_SUB;
    #10;
    $display("  %d - %d = %d (Expected: 15)", operand_a, operand_b, result);
    
    operand_a = 32'd5; operand_b = 32'd5; alu_ctrl = ALU_SUB;
    #10;
    $display("  %d - %d = %d, zero = %b (Expected: 0, zero = 1)", operand_a, operand_b, result, zero);
    
    // Test AND operation
    $display("\nTesting AND operation:");
    operand_a = 32'hF0F0F0F0; operand_b = 32'h0F0F0F0F; alu_ctrl = ALU_AND;
    #10;
    $display("  0x%h & 0x%h = 0x%h (Expected: 0x00000000)", operand_a, operand_b, result);
    
    operand_a = 32'hFFFFFFFF; operand_b = 32'h12345678; alu_ctrl = ALU_AND;
    #10;
    $display("  0x%h & 0x%h = 0x%h (Expected: 0x12345678)", operand_a, operand_b, result);
    
    // Test OR operation
    $display("\nTesting OR operation:");
    operand_a = 32'hF0F0F0F0; operand_b = 32'h0F0F0F0F; alu_ctrl = ALU_OR;
    #10;
    $display("  0x%h | 0x%h = 0x%h (Expected: 0xFFFFFFFF)", operand_a, operand_b, result);
    
    // Test XOR operation
    $display("\nTesting XOR operation:");
    operand_a = 32'hAAAAAAAA; operand_b = 32'h55555555; alu_ctrl = ALU_XOR;
    #10;
    $display("  0x%h ^ 0x%h = 0x%h (Expected: 0xFFFFFFFF)", operand_a, operand_b, result);
    
    // Test SLT (Set Less Than - signed)
    $display("\nTesting SLT operation:");
    operand_a = 32'd10; operand_b = 32'd20; alu_ctrl = ALU_SLT;
    #10;
    $display("  %d < %d = %d (Expected: 1)", $signed(operand_a), $signed(operand_b), result);
    
    operand_a = 32'd20; operand_b = 32'd10; alu_ctrl = ALU_SLT;
    #10;
    $display("  %d < %d = %d (Expected: 0)", $signed(operand_a), $signed(operand_b), result);
    
    operand_a = -32'd5; operand_b = 32'd10; alu_ctrl = ALU_SLT;
    #10;
    $display("  %d < %d = %d (Expected: 1)", $signed(operand_a), $signed(operand_b), result);
    
    // Test SLTU (Set Less Than Unsigned)
    $display("\nTesting SLTU operation:");
    operand_a = 32'd10; operand_b = 32'd20; alu_ctrl = ALU_SLTU;
    #10;
    $display("  %d < %d = %d (unsigned, Expected: 1)", operand_a, operand_b, result);
    
    operand_a = 32'hFFFFFFFF; operand_b = 32'd1; alu_ctrl = ALU_SLTU;
    #10;
    $display("  0x%h < %d = %d (unsigned, Expected: 0)", operand_a, operand_b, result);
    
    // Test SLL (Shift Left Logical)
    $display("\nTesting SLL operation:");
    operand_a = 32'h00000001; operand_b = 32'd4; alu_ctrl = ALU_SLL;
    #10;
    $display("  0x%h << %d = 0x%h (Expected: 0x00000010)", operand_a, operand_b[4:0], result);
    
    operand_a = 32'hAAAAAAAA; operand_b = 32'd1; alu_ctrl = ALU_SLL;
    #10;
    $display("  0x%h << %d = 0x%h (Expected: 0x55555554)", operand_a, operand_b[4:0], result);
    
    // Test SRL (Shift Right Logical)
    $display("\nTesting SRL operation:");
    operand_a = 32'h80000000; operand_b = 32'd4; alu_ctrl = ALU_SRL;
    #10;
    $display("  0x%h >> %d = 0x%h (logical, Expected: 0x08000000)", operand_a, operand_b[4:0], result);
    
    // Test SRA (Shift Right Arithmetic)
    $display("\nTesting SRA operation:");
    operand_a = 32'h80000000; operand_b = 32'd4; alu_ctrl = ALU_SRA;
    #10;
    $display("  0x%h >>> %d = 0x%h (arithmetic, Expected: 0xF8000000)", operand_a, operand_b[4:0], result);
    
    operand_a = 32'h40000000; operand_b = 32'd4; alu_ctrl = ALU_SRA;
    #10;
    $display("  0x%h >>> %d = 0x%h (arithmetic, Expected: 0x04000000)", operand_a, operand_b[4:0], result);
    
    // Test default case
    $display("\nTesting default operation:");
    operand_a = 32'd100; operand_b = 32'd50; alu_ctrl = 4'b1111;
    #10;
    $display("  Invalid operation (ctrl=0x%h) = %d (Expected: 0)", alu_ctrl, result);
    
    $display("\n>>>>>>>>>>>>>>>>>>>>");
    $display("ALU Testbench Complete");
    $finish;
  end
  
  //see changes
  initial begin
    $monitor("Time=%0t | A=0x%h | B=0x%h | Ctrl=%b | Result=0x%h | Zero=%b", 
             $time, operand_a, operand_b, alu_ctrl, result, zero);
  end

endmodule

alu_tb.vcd
$date
	Mon Nov 24 22:10:14 2025
$end
$version
	Icarus Verilog
$end
$timescale
	1ps
$end
$scope module alu_tb $end
$var wire 1 ! zero $end
$var wire 32 " result [31:0] $end
$var parameter 4 # ALU_ADD $end
$var parameter 4 $ ALU_AND $end
$var parameter 4 % ALU_OR $end
$var parameter 4 & ALU_SLL $end
$var parameter 4 ' ALU_SLT $end
$var parameter 4 ( ALU_SLTU $end
$var parameter 4 ) ALU_SRA $end
$var parameter 4 * ALU_SRL $end
$var parameter 4 + ALU_SUB $end
$var parameter 4 , ALU_XOR $end
$var reg 4 - alu_ctrl [3:0] $end
$var reg 32 . operand_a [31:0] $end
$var reg 32 / operand_b [31:0] $end
$scope module dut $end
$var wire 4 0 alu_ctrl [3:0] $end
$var wire 32 1 operand_a [31:0] $end
$var wire 32 2 operand_b [31:0] $end
$var wire 1 ! zero $end
$var parameter 4 3 ALU_ADD $end
$var parameter 4 4 ALU_AND $end
$var parameter 4 5 ALU_OR $end
$var parameter 4 6 ALU_SLL $end
$var parameter 4 7 ALU_SLT $end
$var parameter 4 8 ALU_SLTU $end
$var parameter 4 9 ALU_SRA $end
$var parameter 4 : ALU_SRL $end
$var parameter 4 ; ALU_SUB $end
$var parameter 4 < ALU_XOR $end
$var reg 32 = result [31:0] $end
$upscope $end
$upscope $end
$enddefinitions $end
$comment Show the parameter values. $end
$dumpall
b100 <
b1 ;
b1000 :
b1001 9
b110 8
b101 7
b111 6
b11 5
b10 4
b0 3
b100 ,
b1 +
b1000 *
b1001 )
b110 (
b101 '
b111 &
b11 %
b10 $
b0 #
$end
#0
$dumpvars
b11001 =
b1010 2
b1111 1
b0 0
b1010 /
b1111 .
b0 -
b11001 "
0!
$end
#10000
1!
b0 "
b0 =
b1 /
b1 2
b11111111111111111111111111111111 .
b11111111111111111111111111111111 1
#20000
0!
b1111 "
b1111 =
b1 -
b1 0
b101 /
b101 2
b10100 .
b10100 1
#30000
1!
b0 "
b0 =
b101 .
b101 1
#40000
b10 -
b10 0
b1111000011110000111100001111 /
b1111000011110000111100001111 2
b11110000111100001111000011110000 .
b11110000111100001111000011110000 1
#50000
0!
b10010001101000101011001111000 "
b10010001101000101011001111000 =
b10010001101000101011001111000 /
b10010001101000101011001111000 2
b11111111111111111111111111111111 .
b11111111111111111111111111111111 1
#60000
b11111111111111111111111111111111 "
b11111111111111111111111111111111 =
b11 -
b11 0
b1111000011110000111100001111 /
b1111000011110000111100001111 2
b11110000111100001111000011110000 .
b11110000111100001111000011110000 1
#70000
b100 -
b100 0
b1010101010101010101010101010101 /
b1010101010101010101010101010101 2
b10101010101010101010101010101010 .
b10101010101010101010101010101010 1
#80000
b1 "
b1 =
b101 -
b101 0
b10100 /
b10100 2
b1010 .
b1010 1
#90000
1!
b0 "
b0 =
b1010 /
b1010 2
b10100 .
b10100 1
#100000
0!
b1 "
b1 =
b11111111111111111111111111111011 .
b11111111111111111111111111111011 1
#110000
b110 -
b110 0
b10100 /
b10100 2
b1010 .
b1010 1
#120000
1!
b0 "
b0 =
b1 /
b1 2
b11111111111111111111111111111111 .
b11111111111111111111111111111111 1
#130000
0!
b10000 "
b10000 =
b111 -
b111 0
b100 /
b100 2
b1 .
b1 1
#140000
b1010101010101010101010101010100 "
b1010101010101010101010101010100 =
b1 /
b1 2
b10101010101010101010101010101010 .
b10101010101010101010101010101010 1
#150000
b1000000000000000000000000000 "
b1000000000000000000000000000 =
b1000 -
b1000 0
b100 /
b100 2
b10000000000000000000000000000000 .
b10000000000000000000000000000000 1
#160000
b11111000000000000000000000000000 "
b11111000000000000000000000000000 =
b1001 -
b1001 0
#170000
b100000000000000000000000000 "
b100000000000000000000000000 =
b1000000000000000000000000000000 .
b1000000000000000000000000000000 1
#180000
1!
b0 "
b0 =
b1111 -
b1111 0
b110010 /
b110010 2
b1100100 .
b1100100 1
