bc.v
module bc (
    input  [31:0] d1, //value of rs1
    input  [31:0] d2, //value of rs2
    input         br_un,   // 1 = unsigned compare, 0 = signed compare
    output reg    br_eq,
    output reg    br_l
);

    always @(*) begin
        // Equality flag
        br_eq = (d1 == d2);

        // Less-than flag
        if (br_un)
            br_l = (d1 < d2);   // unsigned compare
        else
            br_l = ($signed(d1) < $signed(d2)); // signed compare
    end

endmodule

bc_tb.v
`timescale 1ns / 1ps

module bc_tb;

  // Inputs
  reg  [31:0] d1;
  reg  [31:0] d2;
  reg  br_un;
  
  // Outputs
  wire br_eq;
  wire br_l;
  
  // Instantiate the branch comparator
  bc dut (
    .d1(d1),
    .d2(d2),
    .br_un(br_un),
    .br_eq(br_eq),
    .br_l(br_l)
  );
  
  // Dump waveforms
  initial begin
    $dumpfile("bc_tb.vcd");
    $dumpvars(0, bc_tb);
  end
  
  // Test cases
  initial begin
    $display("Branch Comparator Testbench");
    $display(">>>>>>>>>>>>>>>>>>>>>>>>>>>>>>>>>\n");
    
    // Test 1: Equal values
    $display("Test 1: Equal values");
    d1 = 32'd100; d2 = 32'd100; br_un = 0;
    #10;
    $display("  d1=%d, d2=%d, signed   -> eq=%b, lt=%b (Expected: eq=1, lt=0)", d1, d2, br_eq, br_l);
    
    d1 = 32'd100; d2 = 32'd100; br_un = 1;
    #10;
    $display("  d1=%d, d2=%d, unsigned -> eq=%b, lt=%b (Expected: eq=1, lt=0)\n", d1, d2, br_eq, br_l);
    
    // Test 2: d1 > d2 (positive numbers)
    $display("Test 2: d1 > d2 (positive)");
    d1 = 32'd200; d2 = 32'd50; br_un = 0;
    #10;
    $display("  d1=%d, d2=%d, signed   -> eq=%b, lt=%b (Expected: eq=0, lt=0)", d1, d2, br_eq, br_l);
    
    d1 = 32'd200; d2 = 32'd50; br_un = 1;
    #10;
    $display("  d1=%d, d2=%d, unsigned -> eq=%b, lt=%b (Expected: eq=0, lt=0)\n", d1, d2, br_eq, br_l);
    
    // Test 3: d1 < d2 (positive numbers)
    $display("Test 3: d1 < d2 (positive)");
    d1 = 32'd50; d2 = 32'd200; br_un = 0;
    #10;
    $display("  d1=%d, d2=%d, signed   -> eq=%b, lt=%b (Expected: eq=0, lt=1)", d1, d2, br_eq, br_l);
    
    d1 = 32'd50; d2 = 32'd200; br_un = 1;
    #10;
    $display("  d1=%d, d2=%d, unsigned -> eq=%b, lt=%b (Expected: eq=0, lt=1)\n", d1, d2, br_eq, br_l);
    
    // Test 4: Signed comparison with negative numbers
    $display("Test 4: Negative vs positive (signed)");
    d1 = -32'd10; d2 = 32'd5; br_un = 0;
    #10;
    $display("  d1=%d, d2=%d, signed   -> eq=%b, lt=%b (Expected: eq=0, lt=1)", $signed(d1), d2, br_eq, br_l);
    
    d1 = 32'd5; d2 = -32'd10; br_un = 0;
    #10;
    $display("  d1=%d, d2=%d, signed   -> eq=%b, lt=%b (Expected: eq=0, lt=0)\n", d1, $signed(d2), br_eq, br_l);
    
    // Test 5: Both negative (signed)
    $display("Test 5: Both negative (signed)");
    d1 = -32'd100; d2 = -32'd50; br_un = 0;
    #10;
    $display("  d1=%d, d2=%d, signed   -> eq=%b, lt=%b (Expected: eq=0, lt=1)", $signed(d1), $signed(d2), br_eq, br_l);
    
    d1 = -32'd50; d2 = -32'd100; br_un = 0;
    #10;
    $display("  d1=%d, d2=%d, signed   -> eq=%b, lt=%b (Expected: eq=0, lt=0)\n", $signed(d1), $signed(d2), br_eq, br_l);
    
    // Test 6: Unsigned comparison with large values
    $display("Test 6: Unsigned comparison (0xFFFFFFFF)");
    d1 = 32'hFFFFFFFF; d2 = 32'd1; br_un = 1;
    #10;
    $display("  d1=0x%h, d2=%d, unsigned -> eq=%b, lt=%b (Expected: eq=0, lt=0)", d1, d2, br_eq, br_l);
    
    d1 = 32'd1; d2 = 32'hFFFFFFFF; br_un = 1;
    #10;
    $display("  d1=%d, d2=0x%h, unsigned -> eq=%b, lt=%b (Expected: eq=0, lt=1)\n", d1, d2, br_eq, br_l);
    
    // Test 7: Same values as Test 6 but signed
    $display("Test 7: Signed comparison (0xFFFFFFFF = -1)");
    d1 = 32'hFFFFFFFF; d2 = 32'd1; br_un = 0;
    #10;
    $display("  d1=%d, d2=%d, signed   -> eq=%b, lt=%b (Expected: eq=0, lt=1)", $signed(d1), d2, br_eq, br_l);
    
    d1 = 32'd1; d2 = 32'hFFFFFFFF; br_un = 0;
    #10;
    $display("  d1=%d, d2=%d, signed   -> eq=%b, lt=%b (Expected: eq=0, lt=0)\n", d1, $signed(d2), br_eq, br_l);
    
    // Test 8: Edge case - zero
    $display("Test 8: Zero comparisons");
    d1 = 32'd0; d2 = 32'd0; br_un = 0;
    #10;
    $display("  d1=%d, d2=%d, signed   -> eq=%b, lt=%b (Expected: eq=1, lt=0)", d1, d2, br_eq, br_l);
    
    d1 = 32'd0; d2 = 32'd5; br_un = 0;
    #10;
    $display("  d1=%d, d2=%d, signed   -> eq=%b, lt=%b (Expected: eq=0, lt=1)", d1, d2, br_eq, br_l);
    
    d1 = -32'd5; d2 = 32'd0; br_un = 0;
    #10;
    $display("  d1=%d, d2=%d, signed   -> eq=%b, lt=%b (Expected: eq=0, lt=1)\n", $signed(d1), d2, br_eq, br_l);
    
    $display(">>>>>>>>>>>>>>>>>>>>>");
    $display("Branch Comparator Test Complete");
    $finish;
  end

endmodule

bc_tb.vcd
$date
	Mon Nov 24 22:15:53 2025
$end
$version
	Icarus Verilog
$end
$timescale
	1ps
$end
$scope module bc_tb $end
$var wire 1 ! br_l $end
$var wire 1 " br_eq $end
$var reg 1 # br_un $end
$var reg 32 $ d1 [31:0] $end
$var reg 32 % d2 [31:0] $end
$scope module dut $end
$var wire 1 # br_un $end
$var wire 32 & d1 [31:0] $end
$var wire 32 ' d2 [31:0] $end
$var reg 1 " br_eq $end
$var reg 1 ! br_l $end
$upscope $end
$upscope $end
$enddefinitions $end
$comment Show the parameter values. $end
$dumpall
$end
#0
$dumpvars
b1100100 '
b1100100 &
b1100100 %
b1100100 $
0#
1"
0!
$end
#10000
1#
#20000
0"
0#
b110010 %
b110010 '
b11001000 $
b11001000 &
#30000
1#
#40000
1!
0#
b11001000 %
b11001000 '
b110010 $
b110010 &
#50000
1#
#60000
0#
b101 %
b101 '
b11111111111111111111111111110110 $
b11111111111111111111111111110110 &
#70000
0!
b11111111111111111111111111110110 %
b11111111111111111111111111110110 '
b101 $
b101 &
#80000
1!
b11111111111111111111111111001110 %
b11111111111111111111111111001110 '
b11111111111111111111111110011100 $
b11111111111111111111111110011100 &
#90000
0!
b11111111111111111111111110011100 %
b11111111111111111111111110011100 '
b11111111111111111111111111001110 $
b11111111111111111111111111001110 &
#100000
1#
b1 %
b1 '
b11111111111111111111111111111111 $
b11111111111111111111111111111111 &
#110000
1!
b11111111111111111111111111111111 %
b11111111111111111111111111111111 '
b1 $
b1 &
#120000
0#
b1 %
b1 '
b11111111111111111111111111111111 $
b11111111111111111111111111111111 &
#130000
0!
b11111111111111111111111111111111 %
b11111111111111111111111111111111 '
b1 $
b1 &
#140000
1"
b0 %
b0 '
b0 $
b0 &
#150000
1!
0"
b101 %
b101 '
#160000
b0 %
b0 '
b11111111111111111111111111111011 $
b11111111111111111111111111111011 &
