control.v
//IMEM to control, decoder
module control (
    input  [31:0] inst, //from IMEM
    output reg [6:0] opcode,  //last 7 LSBs
    output reg [4:0] rd,
    output reg [4:0] rs1,
    output reg [4:0] rs2,
    output reg [2:0] funct3,
    output reg [6:0] funct7,
    //immediates are done in immgen

    //from branch comp
    input br_eq, 
    input br_l,
    
    // Ctrl sigs
  	output reg       pc_sel,
    output reg       reg_write_en,
    output reg       imm_sel,
    output reg       br_un, // 0 is signed, 1 is unsigned
    output reg       b_sel,
    output reg       a_sel,
    output reg [3:0] alu_sel,
    output reg       mem_wr, //0 is read, 1 is write
    output reg [1:0] wb_sel //2 bits for choosing output from ALU vs PC+4 vs MEM read
);

    // Extract instruction fields--need to check table, based on R. Changes below.
    always @(*) begin
        opcode = inst[6:0];
        rd     = inst[11:7];
        funct3 = inst[14:12];
        rs1    = inst[19:15];
        rs2    = inst[24:20];
        funct7 = inst[31:25];
    end

    reg check;
    
    always @(*) begin //Ctrl Signals
        pc_sel = 1'b0;
        reg_write_en = 1'b0;
        imm_sel = 1'b0;
        br_un = 1'b0; //signed
        b_sel = 1'b0;
        a_sel = 1'b0;
        alu_sel = 4'b0000; //10 main calculations, 2^4 = 16;
        mem_wr = 1'b0; //read init
        wb_sel = 2'b0; //select between ALU, PC+4, or DMEM read
        
        case (opcode)
            7'b011_0011: begin //R
                reg_write_en = 1'b1; //read back to rd
                wb_sel = 2'b1; //ALU output
                case ({funct7, funct3})
                    10'b0000000_000: alu_sel = 4'b0000; // ADD
                    10'b0100000_000: alu_sel = 4'b0001; // SUB
                    10'b0000000_100: alu_sel = 4'b0010; // XOR
                    10'b0000000_110: alu_sel = 4'b0011; // OR
                    10'b0000000_111: alu_sel = 4'b0100; // AND
                    10'b0000000_001: alu_sel = 4'b0101; // << Logical
                    10'b0000000_101: alu_sel = 4'b0110; // >> Logical
                    10'b0100000_101: alu_sel = 4'b0111; // >> Arith, msb extends
                    10'b0000000_010: alu_sel = 4'b1000; // Set Less than
                    10'b0000000_011: begin
                        br_un = 1'b1;
                        alu_sel = 4'b1001; // Set Less than (Unsigned), 0-extends
                    end
                    default: alu_sel = 4'b0000;
                endcase
            end
            
            7'b001_0011: begin //Imm Ops (I); R and these ops are exactly the same.
                reg_write_en = 1'b1;
                imm_sel = 1'b1;
                b_sel = 1'b1;
                wb_sel = 2'b1; //ALU output
                case (funct3)
                    3'b000: alu_sel = 4'b0000; //addi
                    3'b100: alu_sel = 4'b0010; //xori
                    3'b110: alu_sel = 4'b0011; //ori
                    3'b111: alu_sel = 4'b0100; //andi
                    3'b001: alu_sel = 4'b0101; //slli
                    3'b101: begin
                        case (inst[30])
                            1'b0: alu_sel = 4'b0110; //srli
                            1'b1: alu_sel = 4'b0111; //srai
                        endcase
                    end
                    3'b010: alu_sel = 4'b1000; //slti
                    3'b011: begin
                        br_un = 1'b1;
                        alu_sel = 4'b1001; //sltiu
                    end
                    default: alu_sel = 4'b0000;
                endcase
            end

            7'b000_0011: begin //Imm LOAD, load M[imm + rs1]
                reg_write_en = 1'b1;
                imm_sel = 1'b1;
                b_sel = 1'b1; //imm
                alu_sel = 4'b0000; //all adding, [imm + rs1]'s addr in DMEM
                mem_wr = 1'b0; //read only
                wb_sel = 2'b0; //MEM READ
            end

            7'b010_0011: begin //STORE store rs2's value into M[imm + rs1]
                imm_sel = 1'b1;
                b_sel = 1'b1;
                alu_sel = 4'b0000; //all adding
                mem_wr = 1'b1; //STORE, WRITE
            end

            7'b110_0011: begin //BRANCH, PC + imm
                br_un = 1'b0; //signed
                imm_sel = 1'b1;
                b_sel   = 1'b1; // immediate
                a_sel   = 1'b1; // PC
                alu_sel = 4'b0000; // PC + imm
                pc_sel  = 1'b0; // default no-branch
                check = 1'b0;

                case (funct3)
                    3'b000: begin
                        if (br_eq == 1'b1)
                            check = 1'b1;
                    end
                    3'b001: begin
                        if (br_eq == 1'b0)
                            check = 1'b1;
                    end
                    3'b100: begin   
                        if (br_l == 1'b1)
                            check = 1'b1;
                    end
                    3'b101: begin
                        if (br_l == 1'b0)
                            check = 1'b1;
                    end
                    3'b110: begin
                        br_un = 1'b1;
                        if (br_l == 1'b1)
                            check = 1'b1;
                    end
                    3'b111: begin
                        br_un = 1'b1;
                        if (br_l == 1'b0)
                            check = 1'b1;
                    end
                    default: begin
                        br_un = 1'b0; //signed
                        check = 1'b0;
                    end
                endcase

                // Final branch decision
                if (check == 1'b1)
                    pc_sel = 1'b1;

            end

            7'b110_1111: begin //jal
                reg_write_en = 1'b1; //rf write
                imm_sel = 1'b1;
                b_sel = 1'b1;
                a_sel = 1'b1;
                pc_sel = 1'b1; //ALU (PC+ imm)
                mem_wr = 1'b0;
                wb_sel = 2'b10; //PC + 4 to rd
            end

            7'b110_0111: begin //jalr
                reg_write_en = 1'b1;
                imm_sel = 1'b1;
                b_sel = 1'b1;
                a_sel = 1'b0; //rs1
                pc_sel = 1'b1;
                mem_wr = 1'b0;
                wb_sel = 2'b10; //PC + 4
            end

            7'b0110111: begin // LUI rd = imm << 12
                reg_write_en = 1'b1;
                imm_sel = 1'b1;       // tell immgen to use U-type
                b_sel = 1'b1;         // choose immediate
                a_sel = 1'b0;         // ALU input A = 0 (x0)
                alu_sel = 4'b0000;  // ALU adds B (the immediate with 0)
                wb_sel = 2'b01;       // write ALU result to rd
            end

            7'b0010111: begin //auipc rd = PC + (imm << 12)
                reg_write_en = 1'b1;
                imm_sel = 1'b1;
                b_sel = 1'b1;
                a_sel = 1'b1;
                alu_sel = 4'b0000; //add
                wb_sel = 2'b01; //alu
            end
        endcase
    end
  // Control Signals
endmodule

control_tb.v
`timescale 1ns / 1ps

module control_tb;

  // Inputs
  reg  [31:0] inst;
  reg         br_eq;
  reg         br_l;
  
  // Outputs
  wire [6:0]  opcode;
  wire [4:0]  rd;
  wire [4:0]  rs1;
  wire [4:0]  rs2;
  wire [2:0]  funct3;
  wire [6:0]  funct7;
  wire        pc_sel;
  wire        reg_write_en;
  wire        imm_sel;
  wire        br_un;
  wire        b_sel;
  wire        a_sel;
  wire [3:0]  alu_sel;
  wire        mem_wr;
  wire [1:0]  wb_sel;
  
  // Instantiate control unit
  control dut (
    .inst(inst),
    .br_eq(br_eq),
    .br_l(br_l),
    .opcode(opcode),
    .rd(rd),
    .rs1(rs1),
    .rs2(rs2),
    .funct3(funct3),
    .funct7(funct7),
    .pc_sel(pc_sel),
    .reg_write_en(reg_write_en),
    .imm_sel(imm_sel),
    .br_un(br_un),
    .b_sel(b_sel),
    .a_sel(a_sel),
    .alu_sel(alu_sel),
    .mem_wr(mem_wr),
    .wb_sel(wb_sel)
  );
  
  // Dump waveforms
  initial begin
    $dumpfile("control_tb.vcd");
    $dumpvars(0, control_tb);
  end
  
  // Helper task to display control signals
  task display_signals;
    input [80*8:1] test_name;
    begin
      $display("  %s", test_name);
      $display("    Instruction fields: opcode=%b rd=%d rs1=%d rs2=%d funct3=%b funct7=%b",
               opcode, rd, rs1, rs2, funct3, funct7);
      $display("    Control signals: pc_sel=%b reg_wr=%b imm_sel=%b br_un=%b",
               pc_sel, reg_write_en, imm_sel, br_un);
      $display("    ALU/MEM: a_sel=%b b_sel=%b alu_sel=%b mem_wr=%b wb_sel=%b",
               a_sel, b_sel, alu_sel, mem_wr, wb_sel);
    end
  endtask
  
  initial begin
    $display("Control Unit Testbench");
    $display(">>>>>>>>>>>>>>>>>>>>\n");
    
    // Initialize branch comparator inputs
    br_eq = 0;
    br_l = 0;
    
    //  R-TYPE INSTRUCTIONS 
    $display("--- R-TYPE Instructions ---");
    
    // ADD: add x1, x2, x3
    inst = 32'b0000000_00011_00010_000_00001_0110011;
    #10;
    display_signals("ADD x1, x2, x3");
    $display("");
    
    // SUB: sub x4, x5, x6
    inst = 32'b0100000_00110_00101_000_00100_0110011;
    #10;
    display_signals("SUB x4, x5, x6");
    $display("");
    
    // XOR: xor x7, x8, x9
    inst = 32'b0000000_01001_01000_100_00111_0110011;
    #10;
    display_signals("XOR x7, x8, x9");
    $display("");
    
    // OR: or x10, x11, x12
    inst = 32'b0000000_01100_01011_110_01010_0110011;
    #10;
    display_signals("OR x10, x11, x12");
    $display("");
    
    // AND: and x13, x14, x15
    inst = 32'b0000000_01111_01110_111_01101_0110011;
    #10;
    display_signals("AND x13, x14, x15");
    $display("");
    
    // SLL: sll x16, x17, x18
    inst = 32'b0000000_10010_10001_001_10000_0110011;
    #10;
    display_signals("SLL x16, x17, x18");
    $display("");
    
    // SRL: srl x19, x20, x21
    inst = 32'b0000000_10101_10100_101_10011_0110011;
    #10;
    display_signals("SRL x19, x20, x21");
    $display("");
    
    // SRA: sra x22, x23, x24
    inst = 32'b0100000_11000_10111_101_10110_0110011;
    #10;
    display_signals("SRA x22, x23, x24");
    $display("");
    
    // SLT: slt x25, x26, x27
    inst = 32'b0000000_11011_11010_010_11001_0110011;
    #10;
    display_signals("SLT x25, x26, x27");
    $display("");
    
    // SLTU: sltu x28, x29, x30
    inst = 32'b0000000_11110_11101_011_11100_0110011;
    #10;
    display_signals("SLTU x28, x29, x30");
    $display("");
    
    //  I-TYPE INSTRUCTIONS 
    $display("--- I-TYPE Instructions (Immediate) ---");
    
    // ADDI: addi x1, x2, 100
    inst = 32'b000001100100_00010_000_00001_0010011;
    #10;
    display_signals("ADDI x1, x2, 100");
    $display("");
    
    // XORI: xori x3, x4, -1
    inst = 32'b111111111111_00100_100_00011_0010011;
    #10;
    display_signals("XORI x3, x4, -1");
    $display("");
    
    // ORI: ori x5, x6, 0xFF
    inst = 32'b000011111111_00110_110_00101_0010011;
    #10;
    display_signals("ORI x5, x6, 0xFF");
    $display("");
    
    // ANDI: andi x7, x8, 0xF0
    inst = 32'b000011110000_01000_111_00111_0010011;
    #10;
    display_signals("ANDI x7, x8, 0xF0");
    $display("");
    
    // SLLI: slli x9, x10, 4
    inst = 32'b0000000_00100_01010_001_01001_0010011;
    #10;
    display_signals("SLLI x9, x10, 4");
    $display("");
    
    // SRLI: srli x11, x12, 2
    inst = 32'b0000000_00010_01100_101_01011_0010011;
    #10;
    display_signals("SRLI x11, x12, 2");
    $display("");
    
    // SRAI: srai x13, x14, 3
    inst = 32'b0100000_00011_01110_101_01101_0010011;
    #10;
    display_signals("SRAI x13, x14, 3");
    $display("");
    
    // SLTI: slti x15, x16, -10
    inst = 32'b111111110110_10000_010_01111_0010011;
    #10;
    display_signals("SLTI x15, x16, -10");
    $display("");
    
    // SLTIU: sltiu x17, x18, 20
    inst = 32'b000000010100_10010_011_10001_0010011;
    #10;
    display_signals("SLTIU x17, x18, 20");
    $display("");
    
    //  LOAD INSTRUCTIONS 
    $display("--- LOAD Instructions ---");
    
    // LW: lw x1, 8(x2)
    inst = 32'b000000001000_00010_010_00001_0000011;
    #10;
    display_signals("LW x1, 8(x2)");
    $display("");
    
    //  STORE INSTRUCTIONS 
    $display("--- STORE Instructions ---");
    
    // SW: sw x3, 12(x4)
    inst = 32'b0000000_00011_00100_010_01100_0100011;
    #10;
    display_signals("SW x3, 12(x4)");
    $display("");
    
    //  BRANCH INSTRUCTIONS 
    $display("--- BRANCH Instructions ---");
    
    // BEQ taken
    $display("  BEQ x5, x6, offset (taken)");
    inst = 32'b0_000010_00110_00101_000_0100_0_1100011;
    br_eq = 1; br_l = 0;
    #10;
    $display("    br_eq=%b br_l=%b -> pc_sel=%b (Expected: 1)", br_eq, br_l, pc_sel);
    $display("");
    
    // BEQ not taken
    $display("  BEQ x5, x6, offset (not taken)");
    inst = 32'b0_000010_00110_00101_000_0100_0_1100011;
    br_eq = 0; br_l = 0;
    #10;
    $display("    br_eq=%b br_l=%b -> pc_sel=%b (Expected: 0)", br_eq, br_l, pc_sel);
    $display("");
    
    // BNE taken
    $display("  BNE x7, x8, offset (taken)");
    inst = 32'b0_000010_01000_00111_001_0100_0_1100011;
    br_eq = 0; br_l = 0;
    #10;
    $display("    br_eq=%b br_l=%b -> pc_sel=%b (Expected: 1)", br_eq, br_l, pc_sel);
    $display("");
    
    // BLT taken
    $display("  BLT x9, x10, offset (taken)");
    inst = 32'b0_000010_01010_01001_100_0100_0_1100011;
    br_eq = 0; br_l = 1;
    #10;
    $display("    br_eq=%b br_l=%b -> pc_sel=%b (Expected: 1)", br_eq, br_l, pc_sel);
    $display("");
    
    // BGE taken
    $display("  BGE x11, x12, offset (taken)");
    inst = 32'b0_000010_01100_01011_101_0100_0_1100011;
    br_eq = 0; br_l = 0;
    #10;
    $display("    br_eq=%b br_l=%b -> pc_sel=%b (Expected: 1)", br_eq, br_l, pc_sel);
    $display("");
    
    // BLTU taken
    $display("  BLTU x13, x14, offset (taken)");
    inst = 32'b0_000010_01110_01101_110_0100_0_1100011;
    br_eq = 0; br_l = 1;
    #10;
    $display("    br_eq=%b br_l=%b br_un=%b -> pc_sel=%b (Expected: br_un=1, pc_sel=1)", 
             br_eq, br_l, br_un, pc_sel);
    $display("");
    
    // BGEU taken
    $display("  BGEU x15, x16, offset (taken)");
    inst = 32'b0_000010_10000_01111_111_0100_0_1100011;
    br_eq = 0; br_l = 0;
    #10;
    $display("    br_eq=%b br_l=%b br_un=%b -> pc_sel=%b (Expected: br_un=1, pc_sel=1)", 
             br_eq, br_l, br_un, pc_sel);
    $display("");
    
    //  JUMP INSTRUCTIONS 
    $display("--- JUMP Instructions ---");
    
    // JAL: jal x1, offset
    inst = 32'b00000000010000000000_00001_1101111;
    br_eq = 0; br_l = 0;
    #10;
    display_signals("JAL x1, offset");
    $display("");
    
    // JALR: jalr x2, x3, 4
    inst = 32'b000000000100_00011_000_00010_1100111;
    #10;
    display_signals("JALR x2, x3, 4");
    $display("");
    
    //  U-TYPE INSTRUCTIONS 
    $display("--- U-TYPE Instructions ---");
    
    // LUI: lui x5, 0x12345
    inst = 32'b00010010001101000101_00101_0110111;
    #10;
    display_signals("LUI x5, 0x12345");
    $display("");
    
    // AUIPC: auipc x6, 0x1000
    inst = 32'b00000001000000000000_00110_0010111;
    #10;
    display_signals("AUIPC x6, 0x1000");
    $display("");
    
    $display(">>>>>>>>>>>>>>>>>>>>");
    $display("Control Unit Test Complete");
    $finish;
  end

endmodule

control_tb.vcd
$date
	Mon Nov 24 22:18:20 2025
$end
$version
	Icarus Verilog
$end
$timescale
	1ps
$end
$scope module control_tb $end
$var wire 2 ! wb_sel [1:0] $end
$var wire 5 " rs2 [4:0] $end
$var wire 5 # rs1 [4:0] $end
$var wire 1 $ reg_write_en $end
$var wire 5 % rd [4:0] $end
$var wire 1 & pc_sel $end
$var wire 7 ' opcode [6:0] $end
$var wire 1 ( mem_wr $end
$var wire 1 ) imm_sel $end
$var wire 7 * funct7 [6:0] $end
$var wire 3 + funct3 [2:0] $end
$var wire 1 , br_un $end
$var wire 1 - b_sel $end
$var wire 4 . alu_sel [3:0] $end
$var wire 1 / a_sel $end
$var reg 1 0 br_eq $end
$var reg 1 1 br_l $end
$var reg 32 2 inst [31:0] $end
$scope module dut $end
$var wire 1 0 br_eq $end
$var wire 1 1 br_l $end
$var wire 32 3 inst [31:0] $end
$var reg 1 / a_sel $end
$var reg 4 4 alu_sel [3:0] $end
$var reg 1 - b_sel $end
$var reg 1 , br_un $end
$var reg 1 5 check $end
$var reg 3 6 funct3 [2:0] $end
$var reg 7 7 funct7 [6:0] $end
$var reg 1 ) imm_sel $end
$var reg 1 ( mem_wr $end
$var reg 7 8 opcode [6:0] $end
$var reg 1 & pc_sel $end
$var reg 5 9 rd [4:0] $end
$var reg 1 $ reg_write_en $end
$var reg 5 : rs1 [4:0] $end
$var reg 5 ; rs2 [4:0] $end
$var reg 2 < wb_sel [1:0] $end
$upscope $end
$scope task display_signals $end
$var reg 640 = test_name [640:1] $end
$upscope $end
$upscope $end
$enddefinitions $end
$comment Show the parameter values. $end
$dumpall
$end
#0
$dumpvars
bx =
b1 <
b11 ;
b10 :
b1 9
b110011 8
b0 7
b0 6
x5
b0 4
b1100010000000010110011 3
b1100010000000010110011 2
01
00
0/
b0 .
0-
0,
b0 +
b0 *
0)
0(
b110011 '
0&
b1 %
1$
b10 #
b11 "
b1 !
$end
#10000
b1 .
b1 4
b1 !
b1 <
1$
b100000 *
b100000 7
b110 "
b110 ;
b101 #
b101 :
b100 %
b100 9
b1000000011000101000001000110011 2
b1000000011000101000001000110011 3
b100000101000100010001000010000001111000001100010010110000100000011110000011001000101100001000000111100000110011 =
#20000
b1 !
b1 <
b10 .
b10 4
1$
b0 *
b0 7
b1001 "
b1001 ;
b1000 #
b1000 :
b100 +
b100 6
b111 %
b111 9
b100101000100001110110011 2
b100101000100001110110011 3
b101001101010101010000100010000001111000001101000010110000100000011110000011010100101100001000000111100000110110 =
#30000
b1 !
b1 <
b11 .
b11 4
1$
b1100 "
b1100 ;
b1011 #
b1011 :
b110 +
b110 6
b1010 %
b1010 9
b110001011110010100110011 2
b110001011110010100110011 3
b101100001001111010100100010000001111000001101110010110000100000011110000011100000101100001000000111100000111001 =
#40000
b1 !
b1 <
b100 .
b100 4
1$
b1111 "
b1111 ;
b1110 #
b1110 :
b111 +
b111 6
b1101 %
b1101 9
b111101110111011010110011 2
b111101110111011010110011 3
b1001111010100100010000001111000001100010011000000101100001000000111100000110001001100010010110000100000011110000011000100110010 =
#50000
b1 !
b1 <
b101 .
b101 4
1$
b10010 "
b10010 ;
b10001 #
b10001 :
b1 +
b1 6
b10000 %
b10000 9
b1001010001001100000110011 2
b1001010001001100000110011 3
b100000101001110010001000010000001111000001100010011001100101100001000000111100000110001001101000010110000100000011110000011000100110101 =
#60000
b1 !
b1 <
b110 .
b110 4
1$
b10101 "
b10101 ;
b10100 #
b10100 :
b101 +
b101 6
b10011 %
b10011 9
b1010110100101100110110011 2
b1010110100101100110110011 3
b101001101001100010011000010000001111000001100010011011000101100001000000111100000110001001101110010110000100000011110000011000100111000 =
#70000
b1 !
b1 <
b111 .
b111 4
1$
b100000 *
b100000 7
b11000 "
b11000 ;
b10111 #
b10111 :
b10110 %
b10110 9
b1000001100010111101101100110011 2
b1000001100010111101101100110011 3
b101001101010010010011000010000001111000001100010011100100101100001000000111100000110010001100000010110000100000011110000011001000110001 =
#80000
b1 !
b1 <
b1000 .
b1000 4
1$
b0 *
b0 7
b11011 "
b11011 ;
b11010 #
b11010 :
b10 +
b10 6
b11001 %
b11001 9
b1101111010010110010110011 2
b1101111010010110010110011 3
b101001101010010010000010010000001111000001100100011001000101100001000000111100000110010001100110010110000100000011110000011001000110100 =
#90000
1,
b1 !
b1 <
b1001 .
b1001 4
1$
b11110 "
b11110 ;
b11101 #
b11101 :
b11 +
b11 6
b11100 %
b11100 9
b1111011101011111000110011 2
b1111011101011111000110011 3
b101001101001100010101000010000001111000001100100011010100101100001000000111100000110010001101100010110000100000011110000011001000110111 =
#100000
1-
1)
b1 !
b1 <
b0 .
b0 4
0,
1$
b11 *
b11 7
b100 "
b100 ;
b10 #
b10 :
b0 +
b0 6
b1 %
b1 9
b10011 '
b10011 8
b110010000010000000010010011 2
b110010000010000000010010011 3
b10100110100110001010100010101010010000001111000001100100011100000101100001000000111100000110010001110010010110000100000011110000011001100110000 =
#110000
b10 .
b10 4
b1 !
b1 <
1-
1)
1$
b1111111 *
b1111111 7
b11111 "
b11111 ;
b100 #
b100 :
b100 +
b100 6
b11 %
b11 9
b11111111111100100100000110010011 2
b11111111111100100100000110010011 3
b1000001010001000100010001001001001000000111100000110001001011000010000001111000001100100010110000100000001100010011000000110000 =
#120000
b1 !
b1 <
b11 .
b11 4
1-
1)
1$
b111 *
b111 7
b110 #
b110 :
b110 +
b110 6
b101 %
b101 9
b1111111100110110001010010011 2
b1111111100110110001010010011 3
b10110000100111101010010010010010010000001111000001100110010110000100000011110000011010000101100001000000010110100110001 =
#130000
b1 !
b1 <
b100 .
b100 4
1-
1)
1$
b10000 "
b10000 ;
b1000 #
b1000 :
b111 +
b111 6
b111 %
b111 9
b1111000001000111001110010011 2
b1111000001000111001110010011 3
b1001111010100100100100100100000011110000011010100101100001000000111100000110110001011000010000000110000011110000100011001000110 =
#140000
b1 !
b1 <
b101 .
b101 4
1-
1)
1$
b0 *
b0 7
b100 "
b100 ;
b1010 #
b1010 :
b1 +
b1 6
b1001 %
b1001 9
b10001010001010010010011 2
b10001010001010010010011 3
b100000101001110010001000100100100100000011110000011011100101100001000000111100000111000001011000010000000110000011110000100011000110000 =
#150000
b1 !
b1 <
b110 .
b110 4
1-
1)
1$
b10 "
b10 ;
b1100 #
b1100 :
b101 +
b101 6
b1011 %
b1011 9
b1001100101010110010011 2
b1001100101010110010011 3
b10100110100110001001100010010010010000001111000001110010010110000100000011110000011000100110000001011000010000000110100 =
#160000
b1 !
b1 <
b111 .
b111 4
1-
1)
1$
b100000 *
b100000 7
b11 "
b11 ;
b1110 #
b1110 :
b1101 %
b1101 9
b1000000001101110101011010010011 2
b1000000001101110101011010010011 3
b1010011010100100100110001001001001000000111100000110001001100010010110000100000011110000011000100110010001011000010000000110010 =
#170000
b1 !
b1 <
b1000 .
b1000 4
1-
1)
1$
b1111111 *
b1111111 7
b10110 "
b10110 ;
b10000 #
b10000 :
b10 +
b10 6
b1111 %
b1111 9
b11111111011010000010011110010011 2
b11111111011010000010011110010011 3
b1010011010100100100000101001001001000000111100000110001001100110010110000100000011110000011000100110100001011000010000000110011 =
#180000
1,
b1 !
b1 <
b1001 .
b1001 4
1-
1)
1$
b0 *
b0 7
b10100 "
b10100 ;
b10010 #
b10010 :
b11 +
b11 6
b10001 %
b10001 9
b1010010010011100010010011 2
b1010010010011100010010011 3
b10100110100110001010100010010010010000001111000001100010011010100101100001000000111100000110001001101100010110000100000001011010011000100110000 =
#190000
b0 !
b0 <
b0 .
b0 4
1-
0,
1)
1$
b1000 "
b1000 ;
b10 #
b10 :
b10 +
b10 6
b1 %
b1 9
b11 '
b11 8
b100000010010000010000011 2
b100000010010000010000011 3
b10100110100110001010100010010010101010100100000011110000011000100110111001011000010000001111000001100010011100000101100001000000011001000110000 =
#200000
1(
1-
1)
0$
b11 "
b11 ;
b100 #
b100 :
b1100 %
b1100 9
b100011 '
b100011 8
b1100100010011000100011 2
b1100100010011000100011 3
b10011000101011100100000011110000011000100101100001000000011100000101000011110000011001000101001 =
#210000
1&
15
1/
0(
1-
1)
b10 *
b10 7
b110 "
b110 ;
b101 #
b101 :
b0 +
b0 6
b1000 %
b1000 9
b1100011 '
b1100011 8
10
b100011000101000010001100011 2
b100011000101000010001100011 3
b1010011010101110010000001111000001100110010110000100000001100010011001000101000011110000011010000101001 =
#220000
05
1/
1-
1)
0&
00
#230000
1&
15
1/
1-
1)
b1000 "
b1000 ;
b111 #
b111 :
b1 +
b1 6
b100100000111001010001100011 2
b100100000111001010001100011 3
#240000
15
1/
1-
1)
1&
b1010 "
b1010 ;
b1001 #
b1001 :
b100 +
b100 6
11
b100101001001100010001100011 2
b100101001001100010001100011 3
#250000
15
1/
1-
1)
1&
b1100 "
b1100 ;
b1011 #
b1011 :
b101 +
b101 6
01
b100110001011101010001100011 2
b100110001011101010001100011 3
#260000
1,
15
1/
1-
1)
1&
b1110 "
b1110 ;
b1101 #
b1101 :
b110 +
b110 6
11
b100111001101110010001100011 2
b100111001101110010001100011 3
#270000
15
1/
1-
1,
1)
1&
b10000 "
b10000 ;
b1111 #
b1111 :
b111 +
b111 6
01
b101000001111111010001100011 2
b101000001111111010001100011 3
#280000
b10 !
b10 <
1$
1/
1-
0,
1)
1&
b0 *
b0 7
b100 "
b100 ;
b0 #
b0 :
b0 +
b0 6
b1 %
b1 9
b1101111 '
b1101111 8
b10000000000000011101111 2
b10000000000000011101111 3
#290000
b10 !
b10 <
0/
1-
1)
1$
1&
b11 #
b11 :
b10 %
b10 9
b1100111 '
b1100111 8
b10000011000000101100111 2
b10000011000000101100111 3
b100101001000001010011000010000001111000001100010010110000100000011011110110011001100110011100110110010101110100 =
#300000
b1 !
b1 <
1-
1)
1$
0&
b1001 *
b1001 7
b11 "
b11 ;
b1000 #
b1000 :
b101 +
b101 6
b101 %
b101 9
b110111 '
b110111 8
b10010001101000101001010110111 2
b10010001101000101001010110111 3
b100101001000001010011000101001000100000011110000011001000101100001000000111100000110011001011000010000000110100 =
#310000
1/
b1 !
b1 <
1-
1)
1$
b0 *
b0 7
b10000 "
b10000 ;
b0 #
b0 :
b0 +
b0 6
b110 %
b110 9
b10111 '
b10111 8
b1000000000000001100010111 2
b1000000000000001100010111 3
b10011000101010101001001001000000111100000110101001011000010000000110000011110000011000100110010001100110011010000110101 =
#320000
b1000001010101010100100101010000010000110010000001111000001101100010110000100000001100000111100000110001001100000011000000110000 =
