dmem.v
module dmem (
    input  clk,
    input  mem_wr,         // 1 = store, 0 = load
    input  [31:0] addr,           // address
    input  [31:0] write_data,     // rs2
    output reg [31:0] read_data
);

    reg [31:0] mem [0:255];   // 1KB data memory for upduino 3.1, memory mapping

    // Synchronous read/write memory
    always @(posedge clk) begin
        if (mem_wr)
            mem[addr[9:2]] <= write_data;   // store
        else
            read_data <= mem[addr[9:2]];    // load only when not writing
    end

endmodule

//git to update and save version; version control

alu.v
///Updiuno ALU
module alu (
    input  [31:0] operand_a,
    input  [31:0] operand_b,
  	input  [3:0]  alu_ctrl,
    output reg [31:0] result,
    output        zero
);
  
// ALUops
localparam ALU_ADD  = 4'b0000;
localparam ALU_SUB  = 4'b0001;
localparam ALU_AND  = 4'b0010;
localparam ALU_OR   = 4'b0011;
localparam ALU_XOR  = 4'b0100;
localparam ALU_SLT  = 4'b0101;  // Set Less Than
localparam ALU_SLTU = 4'b0110;  // Set Less Than Unsigned
localparam ALU_SLL  = 4'b0111;  // Shift Left Logical
localparam ALU_SRL  = 4'b1000;  // Shift Right Logical
localparam ALU_SRA  = 4'b1001;  // Shift Right Arithmetic
  
  always @(*) begin
    case (alu_ctrl) //32 bits
      	ALU_ADD:  result = operand_a + operand_b;
        ALU_SUB:  result = operand_a - operand_b;
        ALU_AND:  result = operand_a & operand_b;
        ALU_OR:   result = operand_a | operand_b;
        ALU_XOR:  result = operand_a ^ operand_b;
        ALU_SLT:  result = ($signed(operand_a) < $signed(operand_b)) ? 32'd1 : 32'd0;
        ALU_SLTU: result = (operand_a < operand_b) ? 32'd1 : 32'd0;
        ALU_SLL:  result = operand_a << operand_b[4:0];
        ALU_SRL:  result = operand_a >> operand_b[4:0];
        ALU_SRA:  result = $signed(operand_a) >>> operand_b[4:0];
        default:  result = 32'd0;
    endcase
  end
  
  assign zero = (result == 32'd0);
  
endmodule

bc.v
module bc (
    input  [31:0] d1, //value of rs1
    input  [31:0] d2, //value of rs2
    input         br_un,   // 1 = unsigned compare, 0 = signed compare
    output reg    br_eq,
    output reg    br_l
);

    always @(*) begin
        // Equality flag
        br_eq = (d1 == d2);

        // Less-than flag
        if (br_un)
            br_l = (d1 < d2);   // unsigned compare
        else
            br_l = ($signed(d1) < $signed(d2)); // signed compare
    end

endmodule

immgen.v
// immgen from inst
module immgen (
    input  [31:0] inst, //from IMEM
    input         imm_sel, //from ctrl
    input  [6:0]  opcode, //from control
    output reg [31:0] imm
);

    always @(*) begin
        imm = 32'd0;

        if (imm_sel) begin
            case (opcode)

                // I-type (ADDI, LW, JALR, etc)
                7'b0010011,
                7'b0000011,
                7'b1100111: begin
                    imm = {{20{inst[31]}}, inst[31:20]};
                end

                // S-type (SW, SH, SB)
                7'b0100011: begin
                    imm = {{20{inst[31]}}, inst[31:25], inst[11:7]};
                end

                // B-type (BEQ, BNE, BLT, etc)
                7'b1100011: begin
                    imm = {{20{inst[31]}}, //one mistake --> was 20 of them, but said it as 19
                           inst[31],
                           inst[7],
                           inst[30:25],
                           inst[11:8],
                           1'b0};
                end

                // J-type (JAL)
                7'b1101111: begin
                    imm = {{11{inst[31]}},
                           inst[31],
                           inst[19:12],
                           inst[20],
                           inst[30:21],
                           1'b0};
                end

                // U-type (LUI, AUIPC)
                7'b0110111,
                7'b0010111: begin
                    imm = {inst[31:12], 12'd0};
                end

                default: imm = 32'd0;

            endcase
        end
    end

endmodule

rf.v
module rf (
    input              clk,
    input              we,
    input      [4:0]   rs1,
    input      [4:0]   rs2,
    input      [4:0]   rd,
    input      [31:0]  wd,
    output     [31:0]  rd1,
    output     [31:0]  rd2
);

    reg [31:0] regs [31:0];
    
    // Initialize all registers to 0
    integer i;
    initial begin
        for (i = 0; i < 32; i = i + 1)
            regs[i] = 32'h00000000;
    end

    // READ PORTS: combinational
    assign rd1 = (rs1 == 0) ? 32'b0 : regs[rs1];
    assign rd2 = (rs2 == 0) ? 32'b0 : regs[rs2];

    // WRITE PORT: synchronous
    always @(posedge clk) begin
        if (we && (rd != 0))
            regs[rd] <= wd;
    end

endmodule

control.v
//IMEM to control, decoder
module control (
    input  [31:0] inst, //from IMEM
    output reg [6:0] opcode,  //last 7 LSBs
    output reg [4:0] rd,
    output reg [4:0] rs1,
    output reg [4:0] rs2,
    output reg [2:0] funct3,
    output reg [6:0] funct7,
    //immediates are done in immgen

    //from branch comp
    input br_eq, 
    input br_l,
    
    // Ctrl sigs
  	output reg       pc_sel,
    output reg       reg_write_en,
    output reg       imm_sel,
    output reg       br_un, // 0 is signed, 1 is unsigned
    output reg       b_sel,
    output reg       a_sel,
    output reg [3:0] alu_sel,
    output reg       mem_wr, //0 is read, 1 is write
    output reg [1:0] wb_sel //2 bits for choosing output from ALU vs PC+4 vs MEM read
);

    // Extract instruction fields--need to check table, based on R. Changes below.
    always @(*) begin
        opcode = inst[6:0];
        rd     = inst[11:7];
        funct3 = inst[14:12];
        rs1    = inst[19:15];
        rs2    = inst[24:20];
        funct7 = inst[31:25];
    end

    reg check;
    
    always @(*) begin //Ctrl Signals
        pc_sel = 1'b0;
        reg_write_en = 1'b0;
        imm_sel = 1'b0;
        br_un = 1'b0; //signed
        b_sel = 1'b0;
        a_sel = 1'b0;
        alu_sel = 4'b0000; //10 main calculations, 2^4 = 16;
        mem_wr = 1'b0; //read init
        wb_sel = 2'b0; //select between ALU, PC+4, or DMEM read
        
        case (opcode)
            7'b011_0011: begin //R
                reg_write_en = 1'b1; //read back to rd
                wb_sel = 2'b1; //ALU output
                case ({funct7, funct3})
                    10'b0000000_000: alu_sel = 4'b0000; // ADD
                    10'b0100000_000: alu_sel = 4'b0001; // SUB
                    10'b0000000_100: alu_sel = 4'b0010; // XOR
                    10'b0000000_110: alu_sel = 4'b0011; // OR
                    10'b0000000_111: alu_sel = 4'b0100; // AND
                    10'b0000000_001: alu_sel = 4'b0101; // << Logical
                    10'b0000000_101: alu_sel = 4'b0110; // >> Logical
                    10'b0100000_101: alu_sel = 4'b0111; // >> Arith, msb extends
                    10'b0000000_010: alu_sel = 4'b1000; // Set Less than
                    10'b0000000_011: begin
                        br_un = 1'b1;
                        alu_sel = 4'b1001; // Set Less than (Unsigned), 0-extends
                    end
                    default: alu_sel = 4'b0000;
                endcase
            end
            
            7'b001_0011: begin //Imm Ops (I); R and these ops are exactly the same.
                reg_write_en = 1'b1;
                imm_sel = 1'b1;
                b_sel = 1'b1;
                wb_sel = 2'b1; //ALU output
                case (funct3)
                    3'b000: alu_sel = 4'b0000; //addi
                    3'b100: alu_sel = 4'b0010; //xori
                    3'b110: alu_sel = 4'b0011; //ori
                    3'b111: alu_sel = 4'b0100; //andi
                    3'b001: alu_sel = 4'b0101; //slli
                    3'b101: begin
                        case (inst[30])
                            1'b0: alu_sel = 4'b0110; //srli
                            1'b1: alu_sel = 4'b0111; //srai
                        endcase
                    end
                    3'b010: alu_sel = 4'b1000; //slti
                    3'b011: begin
                        br_un = 1'b1;
                        alu_sel = 4'b1001; //sltiu
                    end
                    default: alu_sel = 4'b0000;
                endcase
            end

            7'b000_0011: begin //Imm LOAD, load M[imm + rs1]
                reg_write_en = 1'b1;
                imm_sel = 1'b1;
                b_sel = 1'b1; //imm
                alu_sel = 4'b0000; //all adding, [imm + rs1]'s addr in DMEM
                mem_wr = 1'b0; //read only
                wb_sel = 2'b0; //MEM READ
            end

            7'b010_0011: begin //STORE store rs2's value into M[imm + rs1]
                imm_sel = 1'b1;
                b_sel = 1'b1;
                alu_sel = 4'b0000; //all adding
                mem_wr = 1'b1; //STORE, WRITE
            end

            7'b110_0011: begin //BRANCH, PC + imm
                br_un = 1'b0; //signed
                imm_sel = 1'b1;
                b_sel   = 1'b1; // immediate
                a_sel   = 1'b1; // PC
                alu_sel = 4'b0000; // PC + imm
                pc_sel  = 1'b0; // default no-branch
                check = 1'b0;

                case (funct3)
                    3'b000: begin
                        if (br_eq == 1'b1)
                            check = 1'b1;
                    end
                    3'b001: begin
                        if (br_eq == 1'b0)
                            check = 1'b1;
                    end
                    3'b100: begin   
                        if (br_l == 1'b1)
                            check = 1'b1;
                    end
                    3'b101: begin
                        if (br_l == 1'b0)
                            check = 1'b1;
                    end
                    3'b110: begin
                        br_un = 1'b1;
                        if (br_l == 1'b1)
                            check = 1'b1;
                    end
                    3'b111: begin
                        br_un = 1'b1;
                        if (br_l == 1'b0)
                            check = 1'b1;
                    end
                    default: begin
                        br_un = 1'b0; //signed
                        check = 1'b0;
                    end
                endcase

                // Final branch decision
                if (check == 1'b1)
                    pc_sel = 1'b1;

            end

            7'b110_1111: begin //jal
                reg_write_en = 1'b1; //rf write
                imm_sel = 1'b1;
                b_sel = 1'b1;
                a_sel = 1'b1;
                pc_sel = 1'b1; //ALU (PC+ imm)
                mem_wr = 1'b0;
                wb_sel = 2'b10; //PC + 4 to rd
            end

            7'b110_0111: begin //jalr
                reg_write_en = 1'b1;
                imm_sel = 1'b1;
                b_sel = 1'b1;
                a_sel = 1'b0; //rs1
                pc_sel = 1'b1;
                mem_wr = 1'b0;
                wb_sel = 2'b10; //PC + 4
            end

            7'b0110111: begin // LUI rd = imm << 12
                reg_write_en = 1'b1;
                imm_sel = 1'b1;       // tell immgen to use U-type
                b_sel = 1'b1;         // choose immediate
                a_sel = 1'b0;         // ALU input A = 0 (x0)
                alu_sel = 4'b0000;  // ALU adds B (the immediate with 0)
                wb_sel = 2'b01;       // write ALU result to rd
            end

            7'b0010111: begin //auipc rd = PC + (imm << 12)
                reg_write_en = 1'b1;
                imm_sel = 1'b1;
                b_sel = 1'b1;
                a_sel = 1'b1;
                alu_sel = 4'b0000; //add
                wb_sel = 2'b01; //alu
            end
        endcase
    end
  // Control Signals
endmodule

imem.v
module imem (
    input clk,
    input [31:0] addr,
    output reg [31:0] inst
);
    reg [31:0] mem [0:255];

    initial begin
        $readmemh("prog.hex", mem);
    end

    always @(posedge clk) begin
        inst <= mem[addr[9:2]];  // No byte swapping needed!
    end

endmodule

//bottlenecked by BRAM size
//where yosys maps the memory 
//DMA, SPRAM connected to output

pc.v
module pc (
    input clk,
    input reset,
    input pc_sel,
    input [31:0] alu_out,
    output reg [31:0] pc
);
    reg [31:0] next_pc;

    //FSM
    always @(posedge clk or posedge reset) begin
        if (reset)
            pc <= 32'h0000_0000;
        else
            pc <= next_pc;
    end

    //Next PC logic
    always @(*) begin
        if (pc_sel)
            next_pc = alu_out; //branch or jump
        else
            next_pc = pc + 32'd4; //sequential
    end

endmodule

cpu_top.v
module cpu_top (
    input clk,
    input reset,
    
    // Debug outputs for monitoring
    output [31:0] pc_current_out,
    output reg_write_en_out
);

    // ========== Wires and Registers ==========
    
    // PC signals
    wire [31:0] pc_current;
    wire [31:0] pc_plus_4;
    
    // Instruction memory signals
    wire [31:0] instruction;
    
    // Control signals
    wire [6:0] opcode;
    wire [4:0] rd, rs1, rs2;
    wire [2:0] funct3;
    wire [6:0] funct7;
    wire pc_sel;
    wire reg_write_en;
    wire imm_sel;
    wire br_un;
    wire b_sel;
    wire a_sel;
    wire [3:0] alu_sel;
    wire mem_wr;
    wire [1:0] wb_sel;
    
    // Register file signals
    wire [31:0] rf_rd1;
    wire [31:0] rf_rd2;
    wire [31:0] rf_wd;
    
    // Immediate generator signals
    wire [31:0] immediate;
    
    // Branch comparator signals
    wire br_eq;
    wire br_l;
    
    // ALU signals
    wire [31:0] alu_operand_a;
    wire [31:0] alu_operand_b;
    wire [31:0] alu_result;
    wire alu_zero;
    
    // Data memory signals
    wire [31:0] dmem_read_data;
    
    // ========== PC + 4 Computation ==========
    assign pc_plus_4 = pc_current + 32'd4;
    
    // ========== Module Instantiations ==========
    
    // Program Counter
    pc pc_inst (
        .clk(clk),
        .reset(reset),
        .pc_sel(pc_sel),
        .alu_out(alu_result),
        .pc(pc_current)
    );
    
    // Instruction Memory
    imem imem_inst (
        .clk(clk),
        .addr(pc_current),
        .inst(instruction)
    );
    
    // Control Unit
    control control_inst (
        .inst(instruction),
        .opcode(opcode),
        .rd(rd),
        .rs1(rs1),
        .rs2(rs2),
        .funct3(funct3),
        .funct7(funct7),
        .br_eq(br_eq),
        .br_l(br_l),
        .pc_sel(pc_sel),
        .reg_write_en(reg_write_en),
        .imm_sel(imm_sel),
        .br_un(br_un),
        .b_sel(b_sel),
        .a_sel(a_sel),
        .alu_sel(alu_sel),
        .mem_wr(mem_wr),
        .wb_sel(wb_sel)
    );
    
    // Register File
    rf rf_inst (
        .clk(clk),
        .we(reg_write_en),
        .rs1(rs1),
        .rs2(rs2),
        .rd(rd),
        .wd(rf_wd),
        .rd1(rf_rd1),
        .rd2(rf_rd2)
    );
    
    // Immediate Generator
    immgen immgen_inst (
        .inst(instruction),
        .imm_sel(imm_sel),
        .opcode(opcode),
        .imm(immediate)
    );
    
    // Branch Comparator
    bc bc_inst (
        .d1(rf_rd1),
        .d2(rf_rd2),
        .br_un(br_un),
        .br_eq(br_eq),
        .br_l(br_l)
    );
    
    // ALU Operand A Mux (a_sel: 0 = rs1, 1 = PC)
    assign alu_operand_a = a_sel ? pc_current : rf_rd1;
    
    // ALU Operand B Mux (b_sel: 0 = rs2, 1 = immediate)
    assign alu_operand_b = b_sel ? immediate : rf_rd2;
    
    // ALU
    alu alu_inst (
        .operand_a(alu_operand_a),
        .operand_b(alu_operand_b),
        .alu_ctrl(alu_sel),
        .result(alu_result),
        .zero(alu_zero)
    );
    
    // Data Memory
    dmem dmem_inst (
        .clk(clk),
        .mem_wr(mem_wr),
        .addr(alu_result),
        .write_data(rf_rd2),
        .read_data(dmem_read_data)
    );
    
    // ========== Write-back Mux ==========
    // wb_sel: 00 = DMEM, 01 = ALU, 10 = PC+4
    assign rf_wd = (wb_sel == 2'b00) ? dmem_read_data :
                   (wb_sel == 2'b01) ? alu_result :
                   (wb_sel == 2'b10) ? pc_plus_4 :
                   32'd0;
    
    // ========== Debug Outputs ==========
    assign pc_current_out = pc_current;
    assign reg_write_en_out = reg_write_en;

endmodule

cpu_tb.v
`timescale 1ns/1ps

// simple smoke test for cpu_top
module cpu_test;

    reg clk = 0;
    reg reset = 1;

    wire [31:0] pc_out;
    wire reg_wr_out;

    // just a basic clock, 10ns period (100MHz)
    always #5 clk = ~clk;

    // cpu instance we’re testing
    cpu_top cpu (
        .clk(clk),
        .reset(reset),
        .pc_current_out(pc_out),
        .reg_write_en_out(reg_wr_out)
    );

    integer cycle;

    initial begin
        $dumpfile("cpu_tb.vcd");
        $dumpvars(0, cpu_test);

        // hold reset for a lil bit
        #20 reset = 0;

        $display("\n>>>>>> CPU TEST START >>>>>>\n");

        // run for 200 cycles just to see whats going on
        for (cycle = 0; cycle < 200; cycle = cycle + 1) begin
            @(posedge clk);

            // printing PC every cycle like a heartbeat
            $display("Cycle %0d | PC = 0x%08h | RegWrite = %0d",
                     cycle, pc_out, reg_wr_out);

            // if something weird happens (pc not aligned or whatever)
            if (pc_out[1:0] != 2'b00) begin
                $display("Warning: PC not word-aligned lol");
            end
        end

        $display("\n>>>>>> CPU TEST DONE >>>>>>\n");

        $finish;
    end

endmodule

cpu_tb.vcd
$date
	Mon Nov 24 22:55:53 2025
$end
$version
	Icarus Verilog
$end
$timescale
	1ps
$end
$scope module cpu_test $end
$var wire 1 ! reg_wr_out $end
$var wire 32 " pc_out [31:0] $end
$var reg 1 # clk $end
$var reg 1 $ reset $end
$var integer 32 % cycle [31:0] $end
$scope module cpu $end
$var wire 1 # clk $end
$var wire 32 & pc_current_out [31:0] $end
$var wire 1 ! reg_write_en_out $end
$var wire 1 $ reset $end
$var wire 2 ' wb_sel [1:0] $end
$var wire 5 ( rs2 [4:0] $end
$var wire 5 ) rs1 [4:0] $end
$var wire 32 * rf_wd [31:0] $end
$var wire 32 + rf_rd2 [31:0] $end
$var wire 32 , rf_rd1 [31:0] $end
$var wire 1 - reg_write_en $end
$var wire 5 . rd [4:0] $end
$var wire 1 / pc_sel $end
$var wire 32 0 pc_plus_4 [31:0] $end
$var wire 32 1 pc_current [31:0] $end
$var wire 7 2 opcode [6:0] $end
$var wire 1 3 mem_wr $end
$var wire 32 4 instruction [31:0] $end
$var wire 32 5 immediate [31:0] $end
$var wire 1 6 imm_sel $end
$var wire 7 7 funct7 [6:0] $end
$var wire 3 8 funct3 [2:0] $end
$var wire 32 9 dmem_read_data [31:0] $end
$var wire 1 : br_un $end
$var wire 1 ; br_l $end
$var wire 1 < br_eq $end
$var wire 1 = b_sel $end
$var wire 1 > alu_zero $end
$var wire 4 ? alu_sel [3:0] $end
$var wire 32 @ alu_result [31:0] $end
$var wire 32 A alu_operand_b [31:0] $end
$var wire 32 B alu_operand_a [31:0] $end
$var wire 1 C a_sel $end
$scope module alu_inst $end
$var wire 32 D operand_a [31:0] $end
$var wire 32 E operand_b [31:0] $end
$var wire 1 > zero $end
$var wire 4 F alu_ctrl [3:0] $end
$var parameter 4 G ALU_ADD $end
$var parameter 4 H ALU_AND $end
$var parameter 4 I ALU_OR $end
$var parameter 4 J ALU_SLL $end
$var parameter 4 K ALU_SLT $end
$var parameter 4 L ALU_SLTU $end
$var parameter 4 M ALU_SRA $end
$var parameter 4 N ALU_SRL $end
$var parameter 4 O ALU_SUB $end
$var parameter 4 P ALU_XOR $end
$var reg 32 Q result [31:0] $end
$upscope $end
$scope module bc_inst $end
$var wire 32 R d2 [31:0] $end
$var wire 32 S d1 [31:0] $end
$var wire 1 : br_un $end
$var reg 1 < br_eq $end
$var reg 1 ; br_l $end
$upscope $end
$scope module control_inst $end
$var wire 1 < br_eq $end
$var wire 1 ; br_l $end
$var wire 32 T inst [31:0] $end
$var reg 1 C a_sel $end
$var reg 4 U alu_sel [3:0] $end
$var reg 1 = b_sel $end
$var reg 1 : br_un $end
$var reg 1 V check $end
$var reg 3 W funct3 [2:0] $end
$var reg 7 X funct7 [6:0] $end
$var reg 1 6 imm_sel $end
$var reg 1 3 mem_wr $end
$var reg 7 Y opcode [6:0] $end
$var reg 1 / pc_sel $end
$var reg 5 Z rd [4:0] $end
$var reg 1 - reg_write_en $end
$var reg 5 [ rs1 [4:0] $end
$var reg 5 \ rs2 [4:0] $end
$var reg 2 ] wb_sel [1:0] $end
$upscope $end
$scope module dmem_inst $end
$var wire 32 ^ addr [31:0] $end
$var wire 1 # clk $end
$var wire 1 3 mem_wr $end
$var wire 32 _ write_data [31:0] $end
$var reg 32 ` read_data [31:0] $end
$upscope $end
$scope module imem_inst $end
$var wire 1 # clk $end
$var wire 32 a addr [31:0] $end
$var reg 32 b inst [31:0] $end
$upscope $end
$scope module immgen_inst $end
$var wire 1 6 imm_sel $end
$var wire 32 c inst [31:0] $end
$var wire 7 d opcode [6:0] $end
$var reg 32 e imm [31:0] $end
$upscope $end
$scope module pc_inst $end
$var wire 32 f alu_out [31:0] $end
$var wire 1 # clk $end
$var wire 1 / pc_sel $end
$var wire 1 $ reset $end
$var reg 32 g next_pc [31:0] $end
$var reg 32 h pc [31:0] $end
$upscope $end
$scope module rf_inst $end
$var wire 1 # clk $end
$var wire 5 i rd [4:0] $end
$var wire 5 j rs1 [4:0] $end
$var wire 5 k rs2 [4:0] $end
$var wire 32 l wd [31:0] $end
$var wire 1 - we $end
$var wire 32 m rd2 [31:0] $end
$var wire 32 n rd1 [31:0] $end
$var integer 32 o i [31:0] $end
$upscope $end
$upscope $end
$upscope $end
$enddefinitions $end
$comment Show the parameter values. $end
$dumpall
b100 P
b1 O
b1000 N
b1001 M
b110 L
b101 K
b111 J
b11 I
b10 H
b0 G
$end
#0
$dumpvars
b100000 o
bx n
bx m
bx l
bx k
bx j
bx i
b0 h
b100 g
bx f
bx e
bx d
bx c
bx b
b0 a
bx `
bx _
bx ^
bx ]
bx \
bx [
bx Z
bx Y
bx X
bx W
xV
bx U
bx T
bx S
bx R
bx Q
bx F
bx E
bx D
xC
bx B
bx A
bx @
bx ?
x>
x=
x<
x;
x:
bx 9
bx 8
bx 7
x6
bx 5
bx 4
x3
bx 2
b0 1
b100 0
x/
bx .
x-
bx ,
bx +
bx *
bx )
bx (
bx '
b0 &
bx %
1$
0#
b0 "
x!
$end
#5000
b1000000000000 *
b1000000000000 l
0>
b1000000000000 @
b1000000000000 Q
b1000000000000 ^
b1000000000000 f
b0 B
b0 D
0;
1<
b0 +
b0 R
b0 _
b0 m
b0 ,
b0 S
b0 n
b1000000000000 A
b1000000000000 E
b1 '
b1 ]
03
b0 ?
b0 F
b0 U
0C
1=
0:
16
1!
1-
0/
b0 7
b0 X
b0 (
b0 \
b0 k
b0 )
b0 [
b0 j
b1 8
b1 W
b10 .
b10 Z
b10 i
b110111 2
b110111 Y
b110111 d
b1000000000000 5
b1000000000000 e
b1000100110111 4
b1000100110111 T
b1000100110111 b
b1000100110111 c
1#
#10000
0#
#15000
1#
#20000
0#
b0 %
0$
#25000
b1000 g
b1000 0
b100 "
b100 &
b100 1
b100 a
b100 h
b1 %
1#
#30000
0#
#35000
b110100000000 *
b110100000000 l
b1000000000000 B
b1000000000000 D
0<
b110100000000 @
b110100000000 Q
b110100000000 ^
b110100000000 f
b1000000000000 ,
b1000000000000 S
b1000000000000 n
b11111111111111111111110100000000 A
b11111111111111111111110100000000 E
b1 '
b1 ]
1=
16
1!
1-
b1101000 7
b1101000 X
b10 )
b10 [
b10 j
b0 8
b0 W
b10011 2
b10011 Y
b10011 d
b11111111111111111111110100000000 5
b11111111111111111111110100000000 e
b1100 g
b11010000000000010000000100010011 4
b11010000000000010000000100010011 T
b11010000000000010000000100010011 b
b11010000000000010000000100010011 c
b1100 0
b1000 "
b1000 &
b1000 1
b1000 a
b1000 h
b10 %
1#
#40000
0#
#45000
b0 *
b0 l
1>
b0 @
b0 Q
b0 ^
b0 f
1<
b0 A
b0 E
b0 B
b0 D
b1 '
b1 ]
1=
16
1!
1-
b0 7
b0 X
b0 )
b0 [
b0 j
b1 .
b1 Z
b1 i
b0 5
b0 e
b0 ,
b0 S
b0 n
b10000 g
b10010011 4
b10010011 T
b10010011 b
b10010011 c
b10000 0
b1100 "
b1100 &
b1100 1
b1100 a
b1100 h
b11 %
1#
#50000
0#
#55000
b1 *
b1 l
0>
b1 @
b1 Q
b1 ^
b1 f
b1 A
b1 E
b1 '
b1 ]
1=
16
1!
1-
b1 (
b1 \
b1 k
b1 )
b1 [
b1 j
b1 5
b1 e
b10100 g
b100001000000010010011 4
b100001000000010010011 T
b100001000000010010011 b
b100001000000010010011 c
b10100 0
b10000 "
b10000 &
b10000 1
b10000 a
b10000 h
b100 %
1#
#60000
0#
#65000
b1 *
b1 l
b110100000000 A
b110100000000 E
1;
0<
0>
b1 @
b1 Q
b1 ^
b1 f
b1 B
b1 D
b1000 ?
b1000 F
b1000 U
b1 '
b1 ]
0=
06
1!
1-
b10 (
b10 \
b10 k
b10 8
b10 W
b11 .
b11 Z
b11 i
b110011 2
b110011 Y
b110011 d
b0 5
b0 e
b1 ,
b1 S
b1 n
b110100000000 +
b110100000000 R
b110100000000 _
b110100000000 m
b11000 g
b1000001010000110110011 4
b1000001010000110110011 T
b1000001010000110110011 b
b1000001010000110110011 c
b11000 0
b10100 "
b10100 &
b10100 1
b10100 a
b10100 h
b101 %
1#
#70000
0#
#75000
0;
b11000 B
b11000 D
b11111111111111111111111111111000 A
b11111111111111111111111111111000 E
bx *
bx l
b10000 @
b10000 Q
b10000 ^
b10000 f
b0 +
b0 R
b0 _
b0 m
b11111111111111111111111111111000 5
b11111111111111111111111111111000 e
1/
1V
1C
1=
16
b0 '
b0 ]
b0 ?
b0 F
b0 U
0!
0-
b1111111 7
b1111111 X
b0 (
b0 \
b0 k
b11 )
b11 [
b11 j
b1 8
b1 W
b11001 .
b11001 Z
b11001 i
b1100011 2
b1100011 Y
b1100011 d
b10000 g
b11111110000000011001110011100011 4
b11111110000000011001110011100011 T
b11111110000000011001110011100011 b
b11111110000000011001110011100011 c
b11100 0
b11000 "
b11000 &
b11000 1
b11000 a
b11000 h
b110 %
1#
#80000
0#
#85000
1<
b10000 g
b0 ,
b0 S
b0 n
b0 A
b0 E
b10000 @
b10000 Q
b10000 ^
b10000 f
1V
1C
1=
16
1/
b0 7
b0 X
b0 )
b0 [
b0 j
b0 8
b0 W
b0 .
b0 Z
b0 i
b0 5
b0 e
b10000 B
b10000 D
b1100011 4
b1100011 T
b1100011 b
b1100011 c
b10100 0
b10000 "
b10000 &
b10000 1
b10000 a
b10000 h
b111 %
1#
#90000
0#
#95000
b110100000000 A
b110100000000 E
1;
0<
b1 @
b1 Q
b1 ^
b1 f
b1 *
b1 l
b1 B
b1 D
b10100 g
b110100000000 +
b110100000000 R
b110100000000 _
b110100000000 m
b1 ,
b1 S
b1 n
b1000 ?
b1000 F
b1000 U
b1 '
b1 ]
1!
1-
0C
0=
06
0/
b10 (
b10 \
b10 k
b1 )
b1 [
b1 j
b10 8
b10 W
b11 .
b11 Z
b11 i
b110011 2
b110011 Y
b110011 d
b0 5
b0 e
b1000001010000110110011 4
b1000001010000110110011 T
b1000001010000110110011 b
b1000001010000110110011 c
b1000 %
1#
#100000
0#
#105000
b11000 g
b11000 0
b10100 "
b10100 &
b10100 1
b10100 a
b10100 h
b1001 %
1#
#110000
0#
#115000
0;
b11000 B
b11000 D
b11111111111111111111111111111000 A
b11111111111111111111111111111000 E
bx *
bx l
b10000 @
b10000 Q
b10000 ^
b10000 f
b0 +
b0 R
b0 _
b0 m
b11111111111111111111111111111000 5
b11111111111111111111111111111000 e
1/
1V
1C
1=
16
b0 '
b0 ]
b0 ?
b0 F
b0 U
0!
0-
b1111111 7
b1111111 X
b0 (
b0 \
b0 k
b11 )
b11 [
b11 j
b1 8
b1 W
b11001 .
b11001 Z
b11001 i
b1100011 2
b1100011 Y
b1100011 d
b10000 g
b11111110000000011001110011100011 4
b11111110000000011001110011100011 T
b11111110000000011001110011100011 b
b11111110000000011001110011100011 c
b11100 0
b11000 "
b11000 &
b11000 1
b11000 a
b11000 h
b1010 %
1#
#120000
0#
#125000
1<
b10000 g
b0 ,
b0 S
b0 n
b0 A
b0 E
b10000 @
b10000 Q
b10000 ^
b10000 f
1V
1C
1=
16
1/
b0 7
b0 X
b0 )
b0 [
b0 j
b0 8
b0 W
b0 .
b0 Z
b0 i
b0 5
b0 e
b10000 B
b10000 D
b1100011 4
b1100011 T
b1100011 b
b1100011 c
b10100 0
b10000 "
b10000 &
b10000 1
b10000 a
b10000 h
b1011 %
1#
#130000
0#
#135000
b110100000000 A
b110100000000 E
1;
0<
b1 @
b1 Q
b1 ^
b1 f
b1 *
b1 l
b1 B
b1 D
b10100 g
b110100000000 +
b110100000000 R
b110100000000 _
b110100000000 m
b1 ,
b1 S
b1 n
b1000 ?
b1000 F
b1000 U
b1 '
b1 ]
1!
1-
0C
0=
06
0/
b10 (
b10 \
b10 k
b1 )
b1 [
b1 j
b10 8
b10 W
b11 .
b11 Z
b11 i
b110011 2
b110011 Y
b110011 d
b0 5
b0 e
b1000001010000110110011 4
b1000001010000110110011 T
b1000001010000110110011 b
b1000001010000110110011 c
b1100 %
1#
#140000
0#
#145000
b11000 g
b11000 0
b10100 "
b10100 &
b10100 1
b10100 a
b10100 h
b1101 %
1#
#150000
0#
#155000
0;
b11000 B
b11000 D
b11111111111111111111111111111000 A
b11111111111111111111111111111000 E
bx *
bx l
b10000 @
b10000 Q
b10000 ^
b10000 f
b0 +
b0 R
b0 _
b0 m
b11111111111111111111111111111000 5
b11111111111111111111111111111000 e
1/
1V
1C
1=
16
b0 '
b0 ]
b0 ?
b0 F
b0 U
0!
0-
b1111111 7
b1111111 X
b0 (
b0 \
b0 k
b11 )
b11 [
b11 j
b1 8
b1 W
b11001 .
b11001 Z
b11001 i
b1100011 2
b1100011 Y
b1100011 d
b10000 g
b11111110000000011001110011100011 4
b11111110000000011001110011100011 T
b11111110000000011001110011100011 b
b11111110000000011001110011100011 c
b11100 0
b11000 "
b11000 &
b11000 1
b11000 a
b11000 h
b1110 %
1#
#160000
0#
#165000
1<
b10000 g
b0 ,
b0 S
b0 n
b0 A
b0 E
b10000 @
b10000 Q
b10000 ^
b10000 f
1V
1C
1=
16
1/
b0 7
b0 X
b0 )
b0 [
b0 j
b0 8
b0 W
b0 .
b0 Z
b0 i
b0 5
b0 e
b10000 B
b10000 D
b1100011 4
b1100011 T
b1100011 b
b1100011 c
b10100 0
b10000 "
b10000 &
b10000 1
b10000 a
b10000 h
b1111 %
1#
#170000
0#
#175000
b110100000000 A
b110100000000 E
1;
0<
b1 @
b1 Q
b1 ^
b1 f
b1 *
b1 l
b1 B
b1 D
b10100 g
b110100000000 +
b110100000000 R
b110100000000 _
b110100000000 m
b1 ,
b1 S
b1 n
b1000 ?
b1000 F
b1000 U
b1 '
b1 ]
1!
1-
0C
0=
06
0/
b10 (
b10 \
b10 k
b1 )
b1 [
b1 j
b10 8
b10 W
b11 .
b11 Z
b11 i
b110011 2
b110011 Y
b110011 d
b0 5
b0 e
b1000001010000110110011 4
b1000001010000110110011 T
b1000001010000110110011 b
b1000001010000110110011 c
b10000 %
1#
#180000
0#
#185000
b11000 g
b11000 0
b10100 "
b10100 &
b10100 1
b10100 a
b10100 h
b10001 %
1#
#190000
0#
