dmem.v
module dmem (
    input  clk,
    input  mem_wr,         // 1 = store, 0 = load
    input  [31:0] addr,           // address
    input  [31:0] write_data,     // rs2
    output reg [31:0] read_data
);

    reg [31:0] mem [0:255];   // 1KB data memory for upduino 3.1, memory mapping

    // Synchronous read/write memory
    always @(posedge clk) begin
        if (mem_wr)
            mem[addr[9:2]] <= write_data;   // store
        else
            read_data <= mem[addr[9:2]];    // load only when not writing
    end

endmodule

//git to update and save version; version control

dmem_tb.v
`timescale 1ns / 1ps

module dmem_tb;

  // Inputs
  reg         clk;
  reg         mem_wr;
  reg  [31:0] addr;
  reg  [31:0] write_data;
  
  // Outputs
  wire [31:0] read_data;
  
  // Instantiate the data memory
  dmem dut (
    .clk(clk),
    .mem_wr(mem_wr),
    .addr(addr),
    .write_data(write_data),
    .read_data(read_data)
  );
  
  // Clock generation - 10ns period (100MHz)
  initial begin
    clk = 0;
    forever #5 clk = ~clk;
  end
  
  // Dump waveforms
  initial begin
    $dumpfile("dmem_tb.vcd");
    $dumpvars(0, dmem_tb);
  end
  
  // Test procedure
  initial begin
    $display("Data Memory Testbench");
    $display(">>>>>>>\n");
    
    // Initialize
    mem_wr = 0;
    addr = 0;
    write_data = 0;
    
    // Wait for a couple cycles + 1 cycle latency
    repeat(2) @(posedge clk);
    
    // Test 1: Write to address 0
    $display("Test 1: Writing to address 0");
    @(posedge clk);
    addr = 32'h00000000;
    write_data = 32'hDEADBEEF;
    mem_wr = 1;
    $display("  Writing 0x%h to addr 0x%h", write_data, addr);
    
    // Test 2: Read back from address 0
    @(posedge clk);
    mem_wr = 0;
    addr = 32'h00000000;
    $display("  Reading from addr 0x%h...", addr);
    
    @(posedge clk); // Wait for read data to appear
    @(posedge clk); // One more cycle for registered output
    $display("  Read data: 0x%h (Expected: 0xDEADBEEF)\n", read_data);
    
    // Test 3: Write to address 4 (word-aligned)
    $display("Test 2: Writing to address 4");
    @(posedge clk);
    addr = 32'h00000004;
    write_data = 32'h12345678;
    mem_wr = 1;
    $display("  Writing 0x%h to addr 0x%h", write_data, addr);
    
    @(posedge clk);
    mem_wr = 0;
    $display("  Reading from addr 0x%h...", addr);
    
    @(posedge clk);
    @(posedge clk);
    $display("  Read data: 0x%h (Expected: 0x12345678)\n", read_data);
    
    // Test 4: Write to address 8
    $display("Test 3: Writing to address 8");
    @(posedge clk);
    addr = 32'h00000008;
    write_data = 32'hCAFEBABE;
    mem_wr = 1;
    $display("  Writing 0x%h to addr 0x%h", write_data, addr);
    
    @(posedge clk);
    mem_wr = 0;
    $display("  Reading from addr 0x%h...", addr);
    
    @(posedge clk);
    @(posedge clk);
    $display("  Read data: 0x%h (Expected: 0xCAFEBABE)\n", read_data);
    
    // Test 5: Verify old data still exists (read addr 0)
    $display("Test 4: Verify data persistence at address 0");
    @(posedge clk);
    addr = 32'h00000000;
    mem_wr = 0;
    $display("  Reading from addr 0x%h...", addr);
    
    @(posedge clk);
    @(posedge clk);
    $display("  Read data: 0x%h (Expected: 0xDEADBEEF)\n", read_data);
    
    // Test 6: Verify old data at address 4
    $display("Test 5: Verify data persistence at address 4");
    @(posedge clk);
    addr = 32'h00000004;
    $display("  Reading from addr 0x%h...", addr);
    
    @(posedge clk);
    @(posedge clk);
    $display("  Read data: 0x%h (Expected: 0x12345678)\n", read_data);
    
    // Test 7: Overwrite existing data
    $display("Test 6: Overwriting address 0");
    @(posedge clk);
    addr = 32'h00000000;
    write_data = 32'hAAAAAAAA;
    mem_wr = 1;
    $display("  Writing 0x%h to addr 0x%h", write_data, addr);
    
    @(posedge clk);
    mem_wr = 0;
    $display("  Reading from addr 0x%h...", addr);
    
    @(posedge clk);
    @(posedge clk);
    $display("  Read data: 0x%h (Expected: 0xAAAAAAAA)\n", read_data);
    
    // Test 8: Test word alignment (addresses are word-indexed)
    $display("Test 7: Testing word-aligned addressing");
    @(posedge clk);
    addr = 32'h00000010;  // This maps to mem[4]
    write_data = 32'h55555555;
    mem_wr = 1;
    $display("  Writing 0x%h to addr 0x%h (mem[%d])", write_data, addr, addr[9:2]);
    
    @(posedge clk);
    mem_wr = 0;
    $display("  Reading from addr 0x%h...", addr);
    
    @(posedge clk);
    @(posedge clk);
    $display("  Read data: 0x%h (Expected: 0x55555555)\n", read_data);
    
    // Test 9: Maximum address test
    $display("Test 8: Testing near maximum address");
    @(posedge clk);
    addr = 32'h000003FC;  // Last word address (mem[255])
    write_data = 32'hFFFFFFFF;
    mem_wr = 1;
    $display("  Writing 0x%h to addr 0x%h (mem[%d])", write_data, addr, addr[9:2]);
    
    @(posedge clk);
    mem_wr = 0;
    $display("  Reading from addr 0x%h...", addr);
    
    @(posedge clk);
    @(posedge clk);
    $display("  Read data: 0x%h (Expected: 0xFFFFFFFF)\n", read_data);
    
    // Test 10: Read uninitialized memory
    $display("Test 9: Reading uninitialized memory location");
    @(posedge clk);
    addr = 32'h00000100;
    mem_wr = 0;
    $display("  Reading from addr 0x%h...", addr);
    
    @(posedge clk);
    @(posedge clk);
    $display("  Read data: 0x%h (may be x or random)\n", read_data);
    
    // Test 11: Back-to-back writes and reads
    $display("Test 10: Back-to-back operations");
    @(posedge clk);
    addr = 32'h00000020;
    write_data = 32'h99999999;
    mem_wr = 1;
    $display("  Writing 0x%h to addr 0x%h", write_data, addr);
    
    @(posedge clk);
    mem_wr = 0;
    $display("  Immediately reading from same address...");
    
    @(posedge clk);
    @(posedge clk);
    $display("  Read data: 0x%h (Expected: 0x99999999)\n", read_data);
    
    // Wait a few more cycles
    repeat(3) @(posedge clk);
    
    $display(">>>>>>>");
    $display("Data Memory Test Complete");
    $finish;
  end

endmodule

dmem_tb.vcd
$date
	Mon Nov 24 22:28:40 2025
$end
$version
	Icarus Verilog
$end
$timescale
	1ps
$end
$scope module dmem_tb $end
$var wire 32 ! read_data [31:0] $end
$var reg 32 " addr [31:0] $end
$var reg 1 # clk $end
$var reg 1 $ mem_wr $end
$var reg 32 % write_data [31:0] $end
$scope module dut $end
$var wire 32 & addr [31:0] $end
$var wire 1 # clk $end
$var wire 1 $ mem_wr $end
$var wire 32 ' write_data [31:0] $end
$var reg 32 ( read_data [31:0] $end
$upscope $end
$upscope $end
$enddefinitions $end
$comment Show the parameter values. $end
$dumpall
$end
#0
$dumpvars
bx (
b0 '
b0 &
b0 %
0$
0#
b0 "
bx !
$end
#5000
1#
#10000
0#
#15000
1#
#20000
0#
#25000
1$
b11011110101011011011111011101111 %
b11011110101011011011111011101111 '
1#
#30000
0#
#35000
0$
1#
#40000
0#
#45000
b11011110101011011011111011101111 !
b11011110101011011011111011101111 (
1#
#50000
0#
#55000
1#
#60000
0#
#65000
1$
b10010001101000101011001111000 %
b10010001101000101011001111000 '
b100 "
b100 &
1#
#70000
0#
#75000
0$
1#
#80000
0#
#85000
b10010001101000101011001111000 !
b10010001101000101011001111000 (
1#
#90000
0#
#95000
1#
#100000
0#
#105000
1$
b11001010111111101011101010111110 %
b11001010111111101011101010111110 '
b1000 "
b1000 &
1#
#110000
0#
#115000
0$
1#
#120000
0#
#125000
b11001010111111101011101010111110 !
b11001010111111101011101010111110 (
1#
#130000
0#
#135000
1#
#140000
0#
#145000
b11011110101011011011111011101111 !
b11011110101011011011111011101111 (
b0 "
b0 &
1#
#150000
0#
#155000
1#
#160000
0#
#165000
1#
#170000
0#
#175000
b100 "
b100 &
1#
#180000
0#
#185000
b10010001101000101011001111000 !
b10010001101000101011001111000 (
1#
#190000
0#
#195000
1#
#200000
0#
#205000
1$
b10101010101010101010101010101010 %
b10101010101010101010101010101010 '
b0 "
b0 &
1#
#210000
0#
#215000
0$
1#
#220000
0#
#225000
b10101010101010101010101010101010 !
b10101010101010101010101010101010 (
1#
#230000
0#
#235000
1#
#240000
0#
#245000
1$
b1010101010101010101010101010101 %
b1010101010101010101010101010101 '
b10000 "
b10000 &
1#
#250000
0#
#255000
0$
1#
#260000
0#
#265000
b1010101010101010101010101010101 !
b1010101010101010101010101010101 (
1#
#270000
0#
#275000
1#
#280000
0#
#285000
1$
b11111111111111111111111111111111 %
b11111111111111111111111111111111 '
b1111111100 "
b1111111100 &
1#
#290000
0#
#295000
0$
1#
#300000
0#
#305000
b11111111111111111111111111111111 !
b11111111111111111111111111111111 (
1#
#310000
0#
#315000
1#
#320000
0#
#325000
bx !
bx (
b100000000 "
b100000000 &
1#
#330000
0#
#335000
1#
#340000
0#
#345000
1#
#350000
0#
#355000
1$
b10011001100110011001100110011001 %
b10011001100110011001100110011001 '
b100000 "
b100000 &
1#
#360000
0#
#365000
0$
1#
