immgen.v
// immgen from inst
module immgen (
    input  [31:0] inst, //from IMEM
    input         imm_sel, //from ctrl
    input  [6:0]  opcode, //from control
    output reg [31:0] imm
);

    always @(*) begin
        imm = 32'd0;

        if (imm_sel) begin
            case (opcode)

                // I-type (ADDI, LW, JALR, etc)
                7'b0010011,
                7'b0000011,
                7'b1100111: begin
                    imm = {{20{inst[31]}}, inst[31:20]};
                end

                // S-type (SW, SH, SB)
                7'b0100011: begin
                    imm = {{20{inst[31]}}, inst[31:25], inst[11:7]};
                end

                // B-type (BEQ, BNE, BLT, etc)
                7'b1100011: begin
                    imm = {{20{inst[31]}}, //one mistake --> was 20 of them, but said it as 19
                           inst[31],
                           inst[7],
                           inst[30:25],
                           inst[11:8],
                           1'b0};
                end

                // J-type (JAL)
                7'b1101111: begin
                    imm = {{11{inst[31]}},
                           inst[31],
                           inst[19:12],
                           inst[20],
                           inst[30:21],
                           1'b0};
                end

                // U-type (LUI, AUIPC)
                7'b0110111,
                7'b0010111: begin
                    imm = {inst[31:12], 12'd0};
                end

                default: imm = 32'd0;

            endcase
        end
    end

endmodule

immgen_tb.v
`timescale 1ns / 1ps

module immgen_tb;

  reg  [31:0] inst;
  reg         imm_sel;
  reg  [6:0]  opcode;
  wire [31:0] imm;
  
  immgen dut (
    .inst(inst),
    .imm_sel(imm_sel),
    .opcode(opcode),
    .imm(imm)
  );
  
  initial begin
    $dumpfile("immgen_tb.vcd");
    $dumpvars(0, immgen_tb);
  end
  
  // Helper function to create B-type instruction
  function [31:0] make_btype;
    input [12:0] imm_val;  // 13-bit immediate (multiple of 2)
    input [4:0] rs2, rs1;
    input [2:0] funct3;
    begin
      make_btype = {imm_val[12], imm_val[10:5], rs2, rs1, funct3, imm_val[4:1], imm_val[11], 7'b1100011};
    end
  endfunction
  
  // Helper function to create J-type instruction
  function [31:0] make_jtype;
    input [20:0] imm_val;  // 21-bit immediate (multiple of 2)
    input [4:0] rd;
    begin
      make_jtype = {imm_val[20], imm_val[10:1], imm_val[11], imm_val[19:12], rd, 7'b1101111};
    end
  endfunction
  
  initial begin
    $display("Immediate Generator Testbench");
    $display(">>>>>>\n");
    
    // Test with imm_sel = 0
    $display("Test 1: imm_sel = 0 (disabled)");
    imm_sel = 0;
    inst = 32'hFFFFFFFF;
    opcode = 7'b0010011;
    #10;
    $display("  imm=0x%h (Expected: 0x00000000)\n", imm);
    
    imm_sel = 1;
    
    // I-type tests
    $display("Test 2: I-type ADDI x1, x2, 100");
    opcode = 7'b0010011;
    inst = {12'd100, 5'd2, 3'b000, 5'd1, 7'b0010011};
    #10;
    $display("  imm=%d (Expected: 100)\n", $signed(imm));
    
    $display("Test 3: I-type ADDI x1, x2, -1");
    opcode = 7'b0010011;
    inst = {12'hFFF, 5'd2, 3'b000, 5'd1, 7'b0010011};
    #10;
    $display("  imm=%d (Expected: -1)\n", $signed(imm));
    
    $display("Test 4: I-type LW x1, 8(x2)");
    opcode = 7'b0000011;
    inst = {12'd8, 5'd2, 3'b010, 5'd1, 7'b0000011};
    #10;
    $display("  imm=%d (Expected: 8)\n", $signed(imm));
    
    // S-type tests
    $display("Test 5: S-type SW x3, 12(x4)");
    opcode = 7'b0100011;
    inst = {7'd0, 5'd3, 5'd4, 3'b010, 5'd12, 7'b0100011};
    #10;
    $display("  imm=%d (Expected: 12)\n", $signed(imm));
    
    $display("Test 6: S-type SW x3, -4(x4)");
    opcode = 7'b0100011;
    inst = {7'h7F, 5'd3, 5'd4, 3'b010, 5'h1C, 7'b0100011};  // -4 = 0xFFC
    #10;
    $display("  imm=%d (Expected: -4)\n", $signed(imm));
    
    // B-type tests  
    $display("Test 7: B-type BEQ x5, x6, 16");
    opcode = 7'b1100011;
    inst = make_btype(13'd16, 5'd6, 5'd5, 3'b000);
    #10;
    $display("  imm=%d (Expected: 16)\n", $signed(imm));
    
    $display("Test 8: B-type BEQ x5, x6, -4");
    opcode = 7'b1100011;
    inst = make_btype(13'h1FFC, 5'd6, 5'd5, 3'b000);  // -4 in 13 bits
    #10;
    $display("  imm=%d (Expected: -4)\n", $signed(imm));
    
    $display("Test 9: B-type BEQ x5, x6, 32");
    opcode = 7'b1100011;
    inst = make_btype(13'd32, 5'd6, 5'd5, 3'b000);
    #10;
    $display("  imm=%d (Expected: 32)\n", $signed(imm));
    
    // J-type tests
    $display("Test 10: J-type JAL x1, 32");
    opcode = 7'b1101111;
    inst = make_jtype(21'd32, 5'd1);
    #10;
    $display("  imm=%d (Expected: 32)\n", $signed(imm));
    
    $display("Test 11: J-type JAL x1, -4");
    opcode = 7'b1101111;
    inst = make_jtype(21'h1FFFFC, 5'd1);  // -4 in 21 bits
    #10;
    $display("  imm=%d (Expected: -4)\n", $signed(imm));
    
    $display("Test 12: J-type JAL x1, 2048");
    opcode = 7'b1101111;
    inst = make_jtype(21'd2048, 5'd1);
    #10;
    $display("  imm=%d (Expected: 2048)\n", $signed(imm));
    
    // U-type tests
    $display("Test 13: U-type LUI x5, 0x12345");
    opcode = 7'b0110111;
    inst = {20'h12345, 5'd5, 7'b0110111};
    #10;
    $display("  imm=0x%h (Expected: 0x12345000)\n", imm);
    
    $display("Test 14: U-type AUIPC x6, 0x01000");
    opcode = 7'b0010111;
    inst = {20'h01000, 5'd6, 7'b0010111};
    #10;
    $display("  imm=0x%h (Expected: 0x01000000)\n", imm);
    
    $display("\n>>>>>>");
    $display("Immediate Generator Test Complete");
    $finish;
  end

endmodule

immgen_tb.vcd
$date
	Mon Nov 24 22:33:25 2025
$end
$version
	Icarus Verilog
$end
$timescale
	1ps
$end
$scope module immgen_tb $end
$var wire 32 ! imm [31:0] $end
$var reg 1 " imm_sel $end
$var reg 32 # inst [31:0] $end
$var reg 7 $ opcode [6:0] $end
$scope function make_btype $end
$var reg 3 % funct3 [2:0] $end
$var reg 13 & imm_val [12:0] $end
$var reg 5 ' rs1 [4:0] $end
$var reg 5 ( rs2 [4:0] $end
$upscope $end
$scope function make_jtype $end
$var reg 21 ) imm_val [20:0] $end
$var reg 5 * rd [4:0] $end
$upscope $end
$scope module dut $end
$var wire 1 " imm_sel $end
$var wire 32 + inst [31:0] $end
$var wire 7 , opcode [6:0] $end
$var reg 32 - imm [31:0] $end
$upscope $end
$upscope $end
$enddefinitions $end
$comment Show the parameter values. $end
$dumpall
$end
#0
$dumpvars
b0 -
b10011 ,
b11111111111111111111111111111111 +
bx *
bx )
bx (
bx '
bx &
bx %
b10011 $
b11111111111111111111111111111111 #
0"
b0 !
$end
#10000
b1100100 !
b1100100 -
b110010000010000000010010011 #
b110010000010000000010010011 +
1"
#20000
b11111111111111111111111111111111 !
b11111111111111111111111111111111 -
b11111111111100010000000010010011 #
b11111111111100010000000010010011 +
#30000
b1000 !
b1000 -
b100000010010000010000011 #
b100000010010000010000011 +
b11 $
b11 ,
#40000
b1100 !
b1100 -
b1100100010011000100011 #
b1100100010011000100011 +
b100011 $
b100011 ,
#50000
b11111111111111111111111111111100 !
b11111111111111111111111111111100 -
b11111110001100100010111000100011 #
b11111110001100100010111000100011 +
#60000
b10000 !
b10000 -
b11000101000100001100011 #
b11000101000100001100011 +
b10000 &
b110 (
b101 '
b0 %
b1100011 $
b1100011 ,
#70000
b11111111111111111111111111111100 !
b11111111111111111111111111111100 -
b11111110011000101000111011100011 #
b11111110011000101000111011100011 +
b1111111111100 &
#80000
b100000 !
b100000 -
b10011000101000000001100011 #
b10011000101000000001100011 +
b100000 &
#90000
b100000 !
b100000 -
b10000000000000000011101111 #
b10000000000000000011101111 +
b100000 )
b1 *
b1101111 $
b1101111 ,
#100000
b11111111111111111111111111111100 !
b11111111111111111111111111111100 -
b11111111110111111111000011101111 #
b11111111110111111111000011101111 +
b111111111111111111100 )
#110000
b100000000000 !
b100000000000 -
b100000000000011101111 #
b100000000000011101111 +
b100000000000 )
#120000
b10010001101000101000000000000 !
b10010001101000101000000000000 -
b10010001101000101001010110111 #
b10010001101000101001010110111 +
b110111 $
b110111 ,
#130000
b1000000000000000000000000 !
b1000000000000000000000000 -
b1000000000000001100010111 #
b1000000000000001100010111 +
b10111 $
b10111 ,
