pc.v
module pc (
    input clk,
    input reset,
    input pc_sel,
    input [31:0] alu_out,
    output reg [31:0] pc
);
    reg [31:0] next_pc;

    //FSM
    always @(posedge clk or posedge reset) begin
        if (reset)
            pc <= 32'h0000_0000;
        else
            pc <= next_pc;
    end

    //Next PC logic
    always @(*) begin
        if (pc_sel)
            next_pc = alu_out; //branch or jump
        else
            next_pc = pc + 32'd4; //sequential
    end

endmodule

pc_tb.v
`timescale 1ns / 1ps

module pc_tb;

  // Inputs
  reg         clk;
  reg         reset;
  reg         pc_sel;
  reg  [31:0] alu_out;
  
  // Outputs
  wire [31:0] pc;
  
  // Instantiate the PC
  pc dut (
    .clk(clk),
    .reset(reset),
    .pc_sel(pc_sel),
    .alu_out(alu_out),
    .pc(pc)
  );
  
  // Clock generation
  initial begin
    clk = 0;
    forever #5 clk = ~clk;
  end
  
  // Dump waveforms
  initial begin
    $dumpfile("pc_tb.vcd");
    $dumpvars(0, pc_tb);
  end
  
  // Test procedure
  initial begin
    $display("Program Counter Testbench");
    $display("=========================\n");
    
    // Test 1: Reset
    $display("Test 1: Reset");
    reset = 1;
    pc_sel = 0;
    alu_out = 32'hDEADBEEF;
    #10;
    @(posedge clk);
    #1;
    $display("  After reset: PC = 0x%h (Expected: 0x00000000)\n", pc);
    
    // Release reset
    reset = 0;
    
    // Test 2: Sequential execution (PC + 4)
    $display("Test 2: Sequential execution");
    pc_sel = 0;
    alu_out = 32'h12345678;
    
    repeat(5) begin
      @(posedge clk);
      #1;
      $display("  PC = 0x%h", pc);
    end
    $display("  (Expected: 0x00, 0x04, 0x08, 0x0C, 0x10)\n");
    
    // Test 3: Branch/Jump (use ALU output)
    $display("Test 3: Branch to 0x00001000");
    @(posedge clk);
    pc_sel = 1;
    alu_out = 32'h00001000;
    @(posedge clk);
    #1;
    $display("  PC = 0x%h (Expected: 0x00001000)\n", pc);
    
    // Test 4: Continue sequential from new address
    $display("Test 4: Continue sequential from 0x1000");
    pc_sel = 0;
    repeat(3) begin
      @(posedge clk);
      #1;
      $display("  PC = 0x%h", pc);
    end
    $display("  (Expected: 0x1004, 0x1008, 0x100C)\n");
    
    // Test 5: Jump backward
    $display("Test 5: Jump backward to 0x00000100");
    @(posedge clk);
    pc_sel = 1;
    alu_out = 32'h00000100;
    @(posedge clk);
    #1;
    $display("  PC = 0x%h (Expected: 0x00000100)\n", pc);
    
    // Test 6: Sequential from new address
    $display("Test 6: Sequential from 0x100");
    pc_sel = 0;
    repeat(3) begin
      @(posedge clk);
      #1;
      $display("  PC = 0x%h", pc);
    end
    $display("  (Expected: 0x104, 0x108, 0x10C)\n");
    
    // Test 7: Jump to odd address (misaligned)
    $display("Test 7: Jump to misaligned address 0x00000203");
    @(posedge clk);
    pc_sel = 1;
    alu_out = 32'h00000203;
    @(posedge clk);
    #1;
    $display("  PC = 0x%h (Note: misaligned address)\n", pc);
    
    // Test 8: Multiple consecutive branches
    $display("Test 8: Consecutive branches");
    @(posedge clk);
    pc_sel = 1;
    alu_out = 32'h00002000;
    @(posedge clk);
    #1;
    $display("  PC = 0x%h", pc);
    
    @(posedge clk);
    pc_sel = 1;
    alu_out = 32'h00003000;
    @(posedge clk);
    #1;
    $display("  PC = 0x%h", pc);
    
    @(posedge clk);
    pc_sel = 1;
    alu_out = 32'h00004000;
    @(posedge clk);
    #1;
    $display("  PC = 0x%h (Expected: 0x2000, 0x3000, 0x4000)\n", pc);
    
    // Test 9: Reset during execution
    $display("Test 9: Reset during execution");
    pc_sel = 0;
    @(posedge clk);
    @(posedge clk);
    #1;
    $display("  Before reset: PC = 0x%h", pc);
    
    reset = 1;
    @(posedge clk);
    #1;
    $display("  After reset: PC = 0x%h (Expected: 0x00000000)\n", pc);
    
    reset = 0;
    
    // Test 10: pc_sel toggling
    $display("Test 10: Rapid pc_sel changes");
    pc_sel = 0;
    @(posedge clk);
    #1;
    $display("  Sequential: PC = 0x%h", pc);
    
    @(posedge clk);
    pc_sel = 1;
    alu_out = 32'h00005000;
    @(posedge clk);
    #1;
    $display("  Branch: PC = 0x%h", pc);
    
    @(posedge clk);
    pc_sel = 0;
    @(posedge clk);
    #1;
    $display("  Sequential: PC = 0x%h (Expected: 0x5004)\n", pc);
    
    // Wait a few more cycles
    repeat(3) @(posedge clk);
    
    $display("=========================");
    $display("Program Counter Test Complete");
    $finish;
  end
  
  // Monitor
  initial begin
    $monitor("Time=%0t | clk=%b | reset=%b | pc_sel=%b | alu_out=0x%h | pc=0x%h",
             $time, clk, reset, pc_sel, alu_out, pc);
  end

endmodule

pc_tb.vcd
$date
	Mon Nov 24 22:34:36 2025
$end
$version
	Icarus Verilog
$end
$timescale
	1ps
$end
$scope module pc_tb $end
$var wire 32 ! pc [31:0] $end
$var reg 32 " alu_out [31:0] $end
$var reg 1 # clk $end
$var reg 1 $ pc_sel $end
$var reg 1 % reset $end
$scope module dut $end
$var wire 32 & alu_out [31:0] $end
$var wire 1 # clk $end
$var wire 1 $ pc_sel $end
$var wire 1 % reset $end
$var reg 32 ' next_pc [31:0] $end
$var reg 32 ( pc [31:0] $end
$upscope $end
$upscope $end
$enddefinitions $end
$comment Show the parameter values. $end
$dumpall
$end
#0
$dumpvars
b0 (
b100 '
b11011110101011011011111011101111 &
1%
0$
0#
b11011110101011011011111011101111 "
b0 !
$end
#5000
1#
#10000
0#
#15000
1#
#16000
b10010001101000101011001111000 "
b10010001101000101011001111000 &
0%
#20000
0#
#25000
b1000 '
b100 !
b100 (
1#
#30000
0#
#35000
b1100 '
b1000 !
b1000 (
1#
#40000
0#
#45000
b10000 '
b1100 !
b1100 (
1#
#50000
0#
#55000
b10100 '
b10000 !
b10000 (
1#
#60000
0#
#65000
b11000 '
b10100 !
b10100 (
1#
#70000
0#
#75000
b11000 !
b11000 (
b1000000000000 '
b1000000000000 "
b1000000000000 &
1$
1#
#80000
0#
#85000
b1000000000000 !
b1000000000000 (
1#
#86000
b1000000000100 '
0$
#90000
0#
#95000
b1000000001000 '
b1000000000100 !
b1000000000100 (
1#
#100000
0#
#105000
b1000000001100 '
b1000000001000 !
b1000000001000 (
1#
#110000
0#
#115000
b1000000010000 '
b1000000001100 !
b1000000001100 (
1#
#120000
0#
#125000
b1000000010000 !
b1000000010000 (
b100000000 '
b100000000 "
b100000000 &
1$
1#
#130000
0#
#135000
b100000000 !
b100000000 (
1#
#136000
b100000100 '
0$
#140000
0#
#145000
b100001000 '
b100000100 !
b100000100 (
1#
#150000
0#
#155000
b100001100 '
b100001000 !
b100001000 (
1#
#160000
0#
#165000
b100010000 '
b100001100 !
b100001100 (
1#
#170000
0#
#175000
b100010000 !
b100010000 (
b1000000011 '
b1000000011 "
b1000000011 &
1$
1#
#180000
0#
#185000
b1000000011 !
b1000000011 (
1#
#190000
0#
#195000
b10000000000000 '
b10000000000000 "
b10000000000000 &
1#
#200000
0#
#205000
b10000000000000 !
b10000000000000 (
1#
#210000
0#
#215000
b11000000000000 '
b11000000000000 "
b11000000000000 &
1#
#220000
0#
#225000
b11000000000000 !
b11000000000000 (
1#
#230000
0#
#235000
b100000000000000 '
b100000000000000 "
b100000000000000 &
1#
#240000
0#
#245000
b100000000000000 !
b100000000000000 (
1#
#246000
b100000000000100 '
0$
#250000
0#
#255000
b100000000001000 '
b100000000000100 !
b100000000000100 (
1#
#260000
0#
#265000
b100000000001100 '
b100000000001000 !
b100000000001000 (
1#
#266000
b100 '
b0 !
b0 (
1%
#270000
0#
#275000
1#
#276000
0%
#280000
0#
#285000
b1000 '
b100 !
b100 (
1#
#290000
0#
#295000
b1000 !
b1000 (
b101000000000000 '
b101000000000000 "
b101000000000000 &
1$
1#
#300000
0#
#305000
b101000000000000 !
b101000000000000 (
1#
#310000
0#
#315000
b101000000000100 '
0$
1#
#320000
0#
#325000
b101000000001000 '
b101000000000100 !
b101000000000100 (
1#
#330000
0#
#335000
b101000000001100 '
b101000000001000 !
b101000000001000 (
1#
#340000
0#
#345000
b101000000010000 '
b101000000001100 !
b101000000001100 (
1#
#350000
0#
#355000
b101000000010100 '
b101000000010000 !
b101000000010000 (
1#
