rf.v
module rf (
    input              clk,
    input              we,
    input      [4:0]   rs1,
    input      [4:0]   rs2,
    input      [4:0]   rd,
    input      [31:0]  wd,
    output     [31:0]  rd1,
    output     [31:0]  rd2
);

    reg [31:0] regs [31:0];
    
    // Initialize all registers to 0
    integer i;
    initial begin
        for (i = 0; i < 32; i = i + 1)
            regs[i] = 32'h00000000;
    end

    // READ PORTS: combinational
    assign rd1 = (rs1 == 0) ? 32'b0 : regs[rs1];
    assign rd2 = (rs2 == 0) ? 32'b0 : regs[rs2];

    // WRITE PORT: synchronous
    always @(posedge clk) begin
        if (we && (rd != 0))
            regs[rd] <= wd;
    end

endmodule

rf_tb.v
`timescale 1ns/1ps

module rf_tb;

    // basic clock + signals for the register file
    reg clk;
    reg we;
    reg [4:0] rs1, rs2, rd;
    reg [31:0] wd;
    wire [31:0] rd1, rd2;

    // hook up the register file (UUT = unit under test)
    rf uut (
        .clk(clk),
        .we(we),
        .rs1(rs1),
        .rs2(rs2),
        .rd(rd),
        .wd(wd),
        .rd1(rd1),
        .rd2(rd2)
    );

    // generate a 100MHz clock (10ns period), kinda overkill but fine
    initial begin
        clk = 0;
        forever #5 clk = ~clk;
    end

    integer i;
    integer errors;

    // main testing sequence
    initial begin
        $dumpfile("rf_tb.vcd");
        $dumpvars(0, rf_tb);

        // init everything to zero (just being safe)
        errors = 0;
        we = 0;
        rs1 = 0;
        rs2 = 0;
        rd = 0;
        wd = 0;

        // wait a few cycles for stuff to settle
        repeat(3) @(posedge clk);

        $display("\n>>>>>>>");
        $display("Register File Testbench");
        $display(">>>>>>>\n");

        // Test 1: read x0 — always 0 no matter what
        @(negedge clk);
        rs1 = 0;
        rs2 = 0;
        @(posedge clk);
        #1;
        $display("x0 = 0x%08h (Expected 0x00000000)  OK", rd1);
        if (rd1 != 32'h0) errors++;

        // Test 2: write 0xDEADBEEF to x1
        @(negedge clk);
        we = 1;
        rd = 1;
        wd = 32'hDEADBEEF;
        @(posedge clk);

        @(negedge clk);
        we = 0;
        rs1 = 1;
        @(posedge clk);
        #1;
        $display("Read x1 = 0x%08h (Expected 0xDEADBEEF)  OK", rd1);
        if (rd1 != 32'hDEADBEEF) errors++;

        // Test 3: write x2, x3, x4 just making sure everything is consistent
        @(negedge clk);
        we = 1;
        rd = 2;
        wd = 32'h12345678;
        @(posedge clk);

        @(negedge clk);
        rd = 3;
        wd = 32'hCAFEBABE;
        @(posedge clk);

        @(negedge clk);
        rd = 4;
        wd = 32'hAAAAAAAA;
        @(posedge clk);

        @(negedge clk);
        we = 0;

        // read x2
        rs1 = 2;
        @(posedge clk);
        #1;
        $display("x2 = 0x%08h (Expected 0x12345678)  OK", rd1);
        if (rd1 != 32'h12345678) errors++;

        // read x3
        @(negedge clk);
        rs1 = 3;
        @(posedge clk);
        #1;
        $display("x3 = 0x%08h (Expected 0xCAFEBABE)  OK", rd1);
        if (rd1 != 32'hCAFEBABE) errors++;

        // read x4
        @(negedge clk);
        rs1 = 4;
        @(posedge clk);
        #1;
        $display("x4 = 0x%08h (Expected 0xAAAAAAAA)  OK", rd1);
        if (rd1 != 32'hAAAAAAAA) errors++;

        // Test 4: writing to x0 — should ignore write
        @(negedge clk);
        we = 1;
        rd = 0;
        wd = 32'hFFFFFFFF;
        @(posedge clk);

        @(negedge clk);
        we = 0;
        rs1 = 0;
        @(posedge clk);
        #1;
        $display("x0 = 0x%08h (Expected 0x00000000)  OK", rd1);
        if (rd1 != 32'h0) errors++;

        // Test 5: write attempt with we=0 — should not change reg
        @(negedge clk);
        we = 0;
        rd = 6;
        wd = 32'h99999999;
        @(posedge clk);

        @(negedge clk);
        rs1 = 6;
        @(posedge clk);
        #1;
        $display("x6 = 0x%08h (Expected 0x00000000)  OK", rd1);
        if (rd1 != 32'h0) errors++;

        // Test 6: overwrite x1 with a new value
        @(negedge clk);
        we = 1;
        rd = 1;
        wd = 32'h11111111;
        @(posedge clk);

        @(negedge clk);
        we = 0;
        rs1 = 1;
        @(posedge clk);
        #1;
        $display("x1 = 0x%08h (Expected 0x11111111)  OK", rd1);
        if (rd1 != 32'h11111111) errors++;

        // Test 7: dual-read rs1 and rs2 at same time
        @(negedge clk);
        rs1 = 1;
        rs2 = 2;
        @(posedge clk);
        #1;
        $display("x1 = 0x%08h | x2 = 0x%08h", rd1, rd2);
        if (rd1 != 32'h11111111) errors++;
        if (rd2 != 32'h12345678) errors++;

        // Test 8: pattern write to all regs x1–x31
        @(negedge clk);
        we = 1;
        for (i = 1; i < 32; i = i + 1) begin
            @(negedge clk);
            rd = i;
            wd = 32'h10000000 | i;
            @(posedge clk);
        end
        @(negedge clk);
        we = 0;

        // verify pattern
        for (i = 1; i < 32; i = i + 1) begin
            @(negedge clk);
            rs1 = i;
            @(posedge clk);
            #1;
            if (rd1 != (32'h10000000 | i)) begin
                $display("x%02d WRONG (got 0x%08h)", i, rd1);
                errors++;
            end else begin
                $display("x%02d OK", i);
            end
        end

        // Clear all registers so Test 9 can work
        @(negedge clk);
        we = 1;
        for (i = 1; i < 32; i = i + 1) begin
            @(negedge clk);
            rd = i;
            wd = 0;
            @(posedge clk);
        end
        @(negedge clk);
        we = 0;

        // Test 9: back-to-back writes to x7 and x8
        @(negedge clk);
        we = 1;
        rd = 7;
        wd = 32'h77777777;
        @(posedge clk);

        @(negedge clk);
        rd = 8;
        wd = 32'h88888888;
        @(posedge clk);

        @(negedge clk);
        we = 0;

        // verify x7
        rs1 = 7;
        @(posedge clk);
        #1;
        if (rd1 == 32'h77777777)
            $display("x7 = 0x%08h (Expected 0x77777777)  OK", rd1);
        else begin
            errors++;
            $display("x7 WRONG = 0x%08h", rd1);
        end

        // verify x8
        @(negedge clk);
        rs1 = 8;
        @(posedge clk);
        #1;
        if (rd1 == 32'h88888888)
            $display("x8 = 0x%08h (Expected 0x88888888)  OK", rd1);
        else begin
            errors++;
            $display("x8 WRONG = 0x%08h", rd1);
        end

        // Test 10: combinational reads
        @(negedge clk);
        rs1 = 3;
        #1;
        if (rd1 != 32'h0) errors++; // because x3 was cleared
        rs1 = 4;
        #1;
        if (rd1 != 32'h0) errors++;

        repeat(5) @(posedge clk);

        $display("\n>>>>>>>");
        if (errors == 0)
            $display("ALL TESTS PASSED OK");
        else
            $display("FAILED with %0d errors", errors);
        $display(">>>>>>>\n");

        $finish;
    end

    // simple simulation timeout watchdog
    initial begin
        #10000;
        $display("\nERROR: Testbench timeout!");
        $finish;
    end

endmodule

rf_tb.vcd
$date
	Mon Nov 24 22:55:49 2025
$end
$version
	Icarus Verilog
$end
$timescale
	1ps
$end
$scope module rf_tb $end
$var wire 32 ! rd2 [31:0] $end
$var wire 32 " rd1 [31:0] $end
$var reg 1 # clk $end
$var reg 5 $ rd [4:0] $end
$var reg 5 % rs1 [4:0] $end
$var reg 5 & rs2 [4:0] $end
$var reg 32 ' wd [31:0] $end
$var reg 1 ( we $end
$var integer 32 ) errors [31:0] $end
$var integer 32 * i [31:0] $end
$scope module uut $end
$var wire 1 # clk $end
$var wire 5 + rd [4:0] $end
$var wire 5 , rs1 [4:0] $end
$var wire 5 - rs2 [4:0] $end
$var wire 32 . wd [31:0] $end
$var wire 1 ( we $end
$var wire 32 / rd2 [31:0] $end
$var wire 32 0 rd1 [31:0] $end
$var integer 32 1 i [31:0] $end
$upscope $end
$upscope $end
$enddefinitions $end
$comment Show the parameter values. $end
$dumpall
$end
#0
$dumpvars
b100000 1
b0 0
b0 /
b0 .
b0 -
b0 ,
b0 +
bx *
b0 )
0(
b0 '
b0 &
b0 %
b0 $
0#
b0 "
b0 !
$end
#5000
1#
#10000
0#
#15000
1#
#20000
0#
#25000
1#
#30000
0#
#35000
1#
#40000
b11011110101011011011111011101111 '
b11011110101011011011111011101111 .
b1 $
b1 +
1(
0#
#45000
1#
#50000
b11011110101011011011111011101111 "
b11011110101011011011111011101111 0
b1 %
b1 ,
0(
0#
#55000
1#
#60000
b10010001101000101011001111000 '
b10010001101000101011001111000 .
b10 $
b10 +
1(
0#
#65000
1#
#70000
b11001010111111101011101010111110 '
b11001010111111101011101010111110 .
b11 $
b11 +
0#
#75000
1#
#80000
b10101010101010101010101010101010 '
b10101010101010101010101010101010 .
b100 $
b100 +
0#
#85000
1#
#90000
b10010001101000101011001111000 "
b10010001101000101011001111000 0
b10 %
b10 ,
0(
0#
#95000
1#
#100000
b11001010111111101011101010111110 "
b11001010111111101011101010111110 0
b11 %
b11 ,
0#
#105000
1#
#110000
b10101010101010101010101010101010 "
b10101010101010101010101010101010 0
b100 %
b100 ,
0#
#115000
1#
#120000
b11111111111111111111111111111111 '
b11111111111111111111111111111111 .
b0 $
b0 +
1(
0#
#125000
1#
#130000
b0 "
b0 0
b0 %
b0 ,
0(
0#
#135000
1#
#140000
b10011001100110011001100110011001 '
b10011001100110011001100110011001 .
b110 $
b110 +
0#
#145000
1#
#150000
b110 %
b110 ,
0#
#155000
1#
#160000
b10001000100010001000100010001 '
b10001000100010001000100010001 .
b1 $
b1 +
1(
0#
#165000
1#
#170000
b10001000100010001000100010001 "
b10001000100010001000100010001 0
b1 %
b1 ,
0(
0#
#175000
1#
#180000
b10010001101000101011001111000 !
b10010001101000101011001111000 /
b10 &
b10 -
0#
#185000
1#
#190000
b1 *
1(
0#
#195000
1#
#200000
b10000000000000000000000000001 '
b10000000000000000000000000001 .
0#
#205000
b10000000000000000000000000001 "
b10000000000000000000000000001 0
b10 *
1#
#210000
b10000000000000000000000000010 '
b10000000000000000000000000010 .
b10 $
b10 +
0#
#215000
b10000000000000000000000000010 !
b10000000000000000000000000010 /
b11 *
1#
#220000
b10000000000000000000000000011 '
b10000000000000000000000000011 .
b11 $
b11 +
0#
#225000
b100 *
1#
#230000
b10000000000000000000000000100 '
b10000000000000000000000000100 .
b100 $
b100 +
0#
#235000
b101 *
1#
#240000
b10000000000000000000000000101 '
b10000000000000000000000000101 .
b101 $
b101 +
0#
#245000
b110 *
1#
#250000
b10000000000000000000000000110 '
b10000000000000000000000000110 .
b110 $
b110 +
0#
#255000
b111 *
1#
#260000
b10000000000000000000000000111 '
b10000000000000000000000000111 .
b111 $
b111 +
0#
#265000
b1000 *
1#
#270000
b10000000000000000000000001000 '
b10000000000000000000000001000 .
b1000 $
b1000 +
0#
#275000
b1001 *
1#
#280000
b10000000000000000000000001001 '
b10000000000000000000000001001 .
b1001 $
b1001 +
0#
#285000
b1010 *
1#
#290000
b10000000000000000000000001010 '
b10000000000000000000000001010 .
b1010 $
b1010 +
0#
#295000
b1011 *
1#
#300000
b10000000000000000000000001011 '
b10000000000000000000000001011 .
b1011 $
b1011 +
0#
#305000
b1100 *
1#
#310000
b10000000000000000000000001100 '
b10000000000000000000000001100 .
b1100 $
b1100 +
0#
#315000
b1101 *
1#
#320000
b10000000000000000000000001101 '
b10000000000000000000000001101 .
b1101 $
b1101 +
0#
#325000
b1110 *
1#
#330000
b10000000000000000000000001110 '
b10000000000000000000000001110 .
b1110 $
b1110 +
0#
#335000
b1111 *
1#
#340000
b10000000000000000000000001111 '
b10000000000000000000000001111 .
b1111 $
b1111 +
0#
#345000
b10000 *
1#
#350000
b10000000000000000000000010000 '
b10000000000000000000000010000 .
b10000 $
b10000 +
0#
#355000
b10001 *
1#
#360000
b10000000000000000000000010001 '
b10000000000000000000000010001 .
b10001 $
b10001 +
0#
#365000
b10010 *
1#
#370000
b10000000000000000000000010010 '
b10000000000000000000000010010 .
b10010 $
b10010 +
0#
#375000
b10011 *
1#
#380000
b10000000000000000000000010011 '
b10000000000000000000000010011 .
b10011 $
b10011 +
0#
#385000
b10100 *
1#
#390000
b10000000000000000000000010100 '
b10000000000000000000000010100 .
b10100 $
b10100 +
0#
#395000
b10101 *
1#
#400000
b10000000000000000000000010101 '
b10000000000000000000000010101 .
b10101 $
b10101 +
0#
#405000
b10110 *
1#
#410000
b10000000000000000000000010110 '
b10000000000000000000000010110 .
b10110 $
b10110 +
0#
#415000
b10111 *
1#
#420000
b10000000000000000000000010111 '
b10000000000000000000000010111 .
b10111 $
b10111 +
0#
#425000
b11000 *
1#
#430000
b10000000000000000000000011000 '
b10000000000000000000000011000 .
b11000 $
b11000 +
0#
#435000
b11001 *
1#
#440000
b10000000000000000000000011001 '
b10000000000000000000000011001 .
b11001 $
b11001 +
0#
#445000
b11010 *
1#
#450000
b10000000000000000000000011010 '
b10000000000000000000000011010 .
b11010 $
b11010 +
0#
#455000
b11011 *
1#
#460000
b10000000000000000000000011011 '
b10000000000000000000000011011 .
b11011 $
b11011 +
0#
#465000
b11100 *
1#
#470000
b10000000000000000000000011100 '
b10000000000000000000000011100 .
b11100 $
b11100 +
0#
#475000
b11101 *
1#
#480000
b10000000000000000000000011101 '
b10000000000000000000000011101 .
b11101 $
b11101 +
0#
#485000
b11110 *
1#
#490000
b10000000000000000000000011110 '
b10000000000000000000000011110 .
b11110 $
b11110 +
0#
#495000
b11111 *
1#
#500000
b10000000000000000000000011111 '
b10000000000000000000000011111 .
b11111 $
b11111 +
0#
#505000
b100000 *
1#
#510000
b1 *
0(
0#
#515000
1#
#520000
0#
#525000
1#
#526000
b10 *
#530000
b10000000000000000000000000010 "
b10000000000000000000000000010 0
b10 %
b10 ,
0#
#535000
1#
#536000
b11 *
#540000
b10000000000000000000000000011 "
b10000000000000000000000000011 0
b11 %
b11 ,
0#
#545000
1#
#546000
b100 *
#550000
b10000000000000000000000000100 "
b10000000000000000000000000100 0
b100 %
b100 ,
0#
#555000
1#
#556000
b101 *
#560000
b10000000000000000000000000101 "
b10000000000000000000000000101 0
b101 %
b101 ,
0#
#565000
1#
#566000
b110 *
#570000
b10000000000000000000000000110 "
b10000000000000000000000000110 0
b110 %
b110 ,
0#
#575000
1#
#576000
b111 *
#580000
b10000000000000000000000000111 "
b10000000000000000000000000111 0
b111 %
b111 ,
0#
#585000
1#
#586000
b1000 *
#590000
b10000000000000000000000001000 "
b10000000000000000000000001000 0
b1000 %
b1000 ,
0#
#595000
1#
#596000
b1001 *
#600000
b10000000000000000000000001001 "
b10000000000000000000000001001 0
b1001 %
b1001 ,
0#
#605000
1#
#606000
b1010 *
#610000
b10000000000000000000000001010 "
b10000000000000000000000001010 0
b1010 %
b1010 ,
0#
#615000
1#
#616000
b1011 *
#620000
b10000000000000000000000001011 "
b10000000000000000000000001011 0
b1011 %
b1011 ,
0#
#625000
1#
#626000
b1100 *
#630000
b10000000000000000000000001100 "
b10000000000000000000000001100 0
b1100 %
b1100 ,
0#
#635000
1#
#636000
b1101 *
#640000
b10000000000000000000000001101 "
b10000000000000000000000001101 0
b1101 %
b1101 ,
0#
#645000
1#
#646000
b1110 *
#650000
b10000000000000000000000001110 "
b10000000000000000000000001110 0
b1110 %
b1110 ,
0#
#655000
1#
#656000
b1111 *
#660000
b10000000000000000000000001111 "
b10000000000000000000000001111 0
b1111 %
b1111 ,
0#
#665000
1#
#666000
b10000 *
#670000
b10000000000000000000000010000 "
b10000000000000000000000010000 0
b10000 %
b10000 ,
0#
#675000
1#
#676000
b10001 *
#680000
b10000000000000000000000010001 "
b10000000000000000000000010001 0
b10001 %
b10001 ,
0#
#685000
1#
#686000
b10010 *
#690000
b10000000000000000000000010010 "
b10000000000000000000000010010 0
b10010 %
b10010 ,
0#
#695000
1#
#696000
b10011 *
#700000
b10000000000000000000000010011 "
b10000000000000000000000010011 0
b10011 %
b10011 ,
0#
#705000
1#
#706000
b10100 *
#710000
b10000000000000000000000010100 "
b10000000000000000000000010100 0
b10100 %
b10100 ,
0#
#715000
1#
#716000
b10101 *
#720000
b10000000000000000000000010101 "
b10000000000000000000000010101 0
b10101 %
b10101 ,
0#
#725000
1#
#726000
b10110 *
#730000
b10000000000000000000000010110 "
b10000000000000000000000010110 0
b10110 %
b10110 ,
0#
#735000
1#
#736000
b10111 *
#740000
b10000000000000000000000010111 "
b10000000000000000000000010111 0
b10111 %
b10111 ,
0#
#745000
1#
#746000
b11000 *
#750000
b10000000000000000000000011000 "
b10000000000000000000000011000 0
b11000 %
b11000 ,
0#
#755000
1#
#756000
b11001 *
#760000
b10000000000000000000000011001 "
b10000000000000000000000011001 0
b11001 %
b11001 ,
0#
#765000
1#
#766000
b11010 *
#770000
b10000000000000000000000011010 "
b10000000000000000000000011010 0
b11010 %
b11010 ,
0#
#775000
1#
#776000
b11011 *
#780000
b10000000000000000000000011011 "
b10000000000000000000000011011 0
b11011 %
b11011 ,
0#
#785000
1#
#786000
b11100 *
#790000
b10000000000000000000000011100 "
b10000000000000000000000011100 0
b11100 %
b11100 ,
0#
#795000
1#
#796000
b11101 *
#800000
b10000000000000000000000011101 "
b10000000000000000000000011101 0
b11101 %
b11101 ,
0#
#805000
1#
#806000
b11110 *
#810000
b10000000000000000000000011110 "
b10000000000000000000000011110 0
b11110 %
b11110 ,
0#
#815000
1#
#816000
b11111 *
#820000
b10000000000000000000000011111 "
b10000000000000000000000011111 0
b11111 %
b11111 ,
0#
#825000
1#
#826000
b100000 *
#830000
b1 *
1(
0#
#835000
1#
#840000
b0 '
b0 .
b1 $
b1 +
0#
#845000
b10 *
1#
#850000
b10 $
b10 +
0#
#855000
b0 !
b0 /
b11 *
1#
#860000
b11 $
b11 +
0#
#865000
b100 *
1#
#870000
b100 $
b100 +
0#
#875000
b101 *
1#
#880000
b101 $
b101 +
0#
#885000
b110 *
1#
#890000
b110 $
b110 +
0#
#895000
b111 *
1#
#900000
b111 $
b111 +
0#
#905000
b1000 *
1#
#910000
b1000 $
b1000 +
0#
#915000
b1001 *
1#
#920000
b1001 $
b1001 +
0#
#925000
b1010 *
1#
#930000
b1010 $
b1010 +
0#
#935000
b1011 *
1#
#940000
b1011 $
b1011 +
0#
#945000
b1100 *
1#
#950000
b1100 $
b1100 +
0#
#955000
b1101 *
1#
#960000
b1101 $
b1101 +
0#
#965000
b1110 *
1#
#970000
b1110 $
b1110 +
0#
#975000
b1111 *
1#
#980000
b1111 $
b1111 +
0#
#985000
b10000 *
1#
#990000
b10000 $
b10000 +
0#
#995000
b10001 *
1#
#1000000
b10001 $
b10001 +
0#
#1005000
b10010 *
1#
#1010000
b10010 $
b10010 +
0#
#1015000
b10011 *
1#
#1020000
b10011 $
b10011 +
0#
#1025000
b10100 *
1#
#1030000
b10100 $
b10100 +
0#
#1035000
b10101 *
1#
#1040000
b10101 $
b10101 +
0#
#1045000
b10110 *
1#
#1050000
b10110 $
b10110 +
0#
#1055000
b10111 *
1#
#1060000
b10111 $
b10111 +
0#
#1065000
b11000 *
1#
#1070000
b11000 $
b11000 +
0#
#1075000
b11001 *
1#
#1080000
b11001 $
b11001 +
0#
#1085000
b11010 *
1#
#1090000
b11010 $
b11010 +
0#
#1095000
b11011 *
1#
#1100000
b11011 $
b11011 +
0#
#1105000
b11100 *
1#
#1110000
b11100 $
b11100 +
0#
#1115000
b11101 *
1#
#1120000
b11101 $
b11101 +
0#
#1125000
b11110 *
1#
#1130000
b11110 $
b11110 +
0#
#1135000
b11111 *
1#
#1140000
b11111 $
b11111 +
0#
#1145000
b0 "
b0 0
b100000 *
1#
#1150000
0(
0#
#1155000
1#
#1160000
b1110111011101110111011101110111 '
b1110111011101110111011101110111 .
b111 $
b111 +
1(
0#
#1165000
1#
#1170000
b10001000100010001000100010001000 '
b10001000100010001000100010001000 .
b1000 $
b1000 +
0#
#1175000
1#
#1180000
b1110111011101110111011101110111 "
b1110111011101110111011101110111 0
b111 %
b111 ,
0(
0#
#1185000
1#
#1190000
b10001000100010001000100010001000 "
b10001000100010001000100010001000 0
b1000 %
b1000 ,
0#
#1195000
1#
#1200000
b0 "
b0 0
b11 %
b11 ,
0#
#1201000
b100 %
b100 ,
